Demux/Demux_VC0_VC1/probador.v
module probador(		    		input valid_0,
						input valid_1,
						input wire [5:0] dataout0,
						input wire [5:0] dataout1,
						output reg reset_L,
						output reg clk,
						output reg valid_in,
						output reg [5:0] data_in
						);

initial clk <=0;
always begin
	#2 clk <= ~clk;
end

initial begin
	$dumpfile("demux.vcd");
	$dumpvars;

	reset_L <= 1'b0;
	@(posedge clk)
	data_in<=6'h34;
	valid_in<=0;
	reset_L <= 1'b1;

	@(posedge clk)
	data_in <= 6'h32;
	valid_in<=1;

	@(posedge clk)
	data_in <= 6'h37;
	valid_in<=1;

	@(posedge clk)
	data_in <= 6'h7E;
	valid_in<=0;

	@(posedge clk)
	data_in <= 6'h2D;
	valid_in<=0;

	@(posedge clk)
	data_in <= 6'h12;
	valid_in<=1;

	@(posedge clk)
	data_in <= 6'h13;
	valid_in<=1;

	@(posedge clk)
	reset_L <= 1'b0;

	@(posedge clk)
	reset_L <= 1'b1;

	@(posedge clk)
	data_in <= 6'h23;
	valid_in<=1;

	@(posedge clk)
	data_in <= 6'h4;
	valid_in<=1;

	@(posedge clk)
	data_in <= 6'h25;
	valid_in<=0;

	#30 $finish;
end

endmodule

Demux/Demux/demuxEstructural.v
/* Generated by Yosys 0.7 (git sha1 61f6811, gcc 6.2.0-11ubuntu1 -O2 -fdebug-prefix-map=/build/yosys-zWLHjG/yosys-0.7=. -fstack-protector-strong -fPIC -Os) */

module demuxEstructural(clk, reset_L, valid_in, data_in, dataout0, dataout1, valid_0, valid_1);
  wire [5:0] _000_;
  wire [5:0] _001_;
  wire _002_;
  wire _003_;
  wire _004_;
  wire _005_;
  wire _006_;
  wire _007_;
  wire _008_;
  wire _009_;
  wire _010_;
  wire _011_;
  wire _012_;
  wire _013_;
  wire _014_;
  wire _015_;
  wire _016_;
  wire _017_;
  wire _018_;
  wire _019_;
  wire _020_;
  wire _021_;
  wire _022_;
  wire _023_;
  wire _024_;
  wire _025_;
  wire _026_;
  wire _027_;
  wire _028_;
  wire _029_;
  wire _030_;
  wire _031_;
  wire _032_;
  wire _033_;
  wire _034_;
  wire _035_;
  wire _036_;
  wire _037_;
  wire _038_;
  wire _039_;
  wire _040_;
  wire _041_;
  wire _042_;
  wire _043_;
  wire _044_;
  wire _045_;
  wire _046_;
  wire _047_;
  wire _048_;
  wire _049_;
  wire _050_;
  wire _051_;
  wire _052_;
  wire _053_;
  input clk;
  input [5:0] data_in;
  output [5:0] dataout0;
  output [5:0] dataout1;
  input reset_L;
  output valid_0;
  output valid_1;
  input valid_in;
  NOT _054_ (
    .A(data_in[5]),
    .Y(_004_)
  );
  NAND _055_ (
    .A(valid_in),
    .B(reset_L),
    .Y(_005_)
  );
  NOR _056_ (
    .A(_005_),
    .B(_004_),
    .Y(_003_)
  );
  NOR _057_ (
    .A(_005_),
    .B(data_in[5]),
    .Y(_002_)
  );
  NOR _058_ (
    .A(valid_1),
    .B(valid_in),
    .Y(_006_)
  );
  NOR _059_ (
    .A(_006_),
    .B(_003_),
    .Y(_007_)
  );
  NOT _060_ (
    .A(reset_L),
    .Y(_008_)
  );
  NOT _061_ (
    .A(dataout1[0]),
    .Y(_009_)
  );
  NOR _062_ (
    .A(_009_),
    .B(_008_),
    .Y(_010_)
  );
  NAND _063_ (
    .A(_010_),
    .B(_007_),
    .Y(_011_)
  );
  NAND _064_ (
    .A(_003_),
    .B(data_in[0]),
    .Y(_012_)
  );
  NAND _065_ (
    .A(_012_),
    .B(_011_),
    .Y(_001_[0])
  );
  NOT _066_ (
    .A(dataout1[1]),
    .Y(_013_)
  );
  NOR _067_ (
    .A(_013_),
    .B(_008_),
    .Y(_014_)
  );
  NAND _068_ (
    .A(_014_),
    .B(_007_),
    .Y(_015_)
  );
  NAND _069_ (
    .A(_003_),
    .B(data_in[1]),
    .Y(_016_)
  );
  NAND _070_ (
    .A(_016_),
    .B(_015_),
    .Y(_001_[1])
  );
  NOT _071_ (
    .A(dataout1[2]),
    .Y(_017_)
  );
  NOR _072_ (
    .A(_017_),
    .B(_008_),
    .Y(_018_)
  );
  NAND _073_ (
    .A(_018_),
    .B(_007_),
    .Y(_019_)
  );
  NAND _074_ (
    .A(_003_),
    .B(data_in[2]),
    .Y(_020_)
  );
  NAND _075_ (
    .A(_020_),
    .B(_019_),
    .Y(_001_[2])
  );
  NOT _076_ (
    .A(dataout1[3]),
    .Y(_021_)
  );
  NOR _077_ (
    .A(_021_),
    .B(_008_),
    .Y(_022_)
  );
  NAND _078_ (
    .A(_022_),
    .B(_007_),
    .Y(_023_)
  );
  NAND _079_ (
    .A(_003_),
    .B(data_in[3]),
    .Y(_024_)
  );
  NAND _080_ (
    .A(_024_),
    .B(_023_),
    .Y(_001_[3])
  );
  NOT _081_ (
    .A(dataout1[4]),
    .Y(_025_)
  );
  NOR _082_ (
    .A(_025_),
    .B(_008_),
    .Y(_026_)
  );
  NAND _083_ (
    .A(_026_),
    .B(_007_),
    .Y(_027_)
  );
  NAND _084_ (
    .A(_003_),
    .B(data_in[4]),
    .Y(_028_)
  );
  NAND _085_ (
    .A(_028_),
    .B(_027_),
    .Y(_001_[4])
  );
  NOT _086_ (
    .A(valid_in),
    .Y(_029_)
  );
  NOR _087_ (
    .A(_029_),
    .B(_008_),
    .Y(_030_)
  );
  NAND _088_ (
    .A(_030_),
    .B(data_in[5]),
    .Y(_031_)
  );
  NOT _089_ (
    .A(_006_),
    .Y(_032_)
  );
  NOT _090_ (
    .A(dataout1[5]),
    .Y(_033_)
  );
  NOR _091_ (
    .A(_033_),
    .B(_008_),
    .Y(_034_)
  );
  NAND _092_ (
    .A(_034_),
    .B(_032_),
    .Y(_035_)
  );
  NAND _093_ (
    .A(_035_),
    .B(_031_),
    .Y(_001_[5])
  );
  NAND _094_ (
    .A(_002_),
    .B(data_in[0]),
    .Y(_036_)
  );
  NOR _095_ (
    .A(valid_in),
    .B(_008_),
    .Y(_037_)
  );
  NAND _096_ (
    .A(_037_),
    .B(valid_0),
    .Y(_038_)
  );
  NAND _097_ (
    .A(_038_),
    .B(_031_),
    .Y(_039_)
  );
  NAND _098_ (
    .A(_039_),
    .B(dataout0[0]),
    .Y(_040_)
  );
  NAND _099_ (
    .A(_040_),
    .B(_036_),
    .Y(_000_[0])
  );
  NAND _100_ (
    .A(_002_),
    .B(data_in[1]),
    .Y(_041_)
  );
  NAND _101_ (
    .A(_039_),
    .B(dataout0[1]),
    .Y(_042_)
  );
  NAND _102_ (
    .A(_042_),
    .B(_041_),
    .Y(_000_[1])
  );
  NAND _103_ (
    .A(_002_),
    .B(data_in[2]),
    .Y(_043_)
  );
  NAND _104_ (
    .A(_039_),
    .B(dataout0[2]),
    .Y(_044_)
  );
  NAND _105_ (
    .A(_044_),
    .B(_043_),
    .Y(_000_[2])
  );
  NAND _106_ (
    .A(_002_),
    .B(data_in[3]),
    .Y(_045_)
  );
  NAND _107_ (
    .A(_039_),
    .B(dataout0[3]),
    .Y(_046_)
  );
  NAND _108_ (
    .A(_046_),
    .B(_045_),
    .Y(_000_[3])
  );
  NAND _109_ (
    .A(_002_),
    .B(data_in[4]),
    .Y(_047_)
  );
  NAND _110_ (
    .A(_039_),
    .B(dataout0[4]),
    .Y(_048_)
  );
  NAND _111_ (
    .A(_048_),
    .B(_047_),
    .Y(_000_[4])
  );
  NOT _112_ (
    .A(dataout0[5]),
    .Y(_049_)
  );
  NOT _113_ (
    .A(valid_0),
    .Y(_050_)
  );
  NAND _114_ (
    .A(_029_),
    .B(reset_L),
    .Y(_051_)
  );
  NOR _115_ (
    .A(_051_),
    .B(_050_),
    .Y(_052_)
  );
  NOR _116_ (
    .A(_052_),
    .B(_003_),
    .Y(_053_)
  );
  NOR _117_ (
    .A(_053_),
    .B(_049_),
    .Y(_000_[5])
  );
  DFF _118_ (
    .C(clk),
    .D(_000_[0]),
    .Q(dataout0[0])
  );
  DFF _119_ (
    .C(clk),
    .D(_000_[1]),
    .Q(dataout0[1])
  );
  DFF _120_ (
    .C(clk),
    .D(_000_[2]),
    .Q(dataout0[2])
  );
  DFF _121_ (
    .C(clk),
    .D(_000_[3]),
    .Q(dataout0[3])
  );
  DFF _122_ (
    .C(clk),
    .D(_000_[4]),
    .Q(dataout0[4])
  );
  DFF _123_ (
    .C(clk),
    .D(_000_[5]),
    .Q(dataout0[5])
  );
  DFF _124_ (
    .C(clk),
    .D(_001_[0]),
    .Q(dataout1[0])
  );
  DFF _125_ (
    .C(clk),
    .D(_001_[1]),
    .Q(dataout1[1])
  );
  DFF _126_ (
    .C(clk),
    .D(_001_[2]),
    .Q(dataout1[2])
  );
  DFF _127_ (
    .C(clk),
    .D(_001_[3]),
    .Q(dataout1[3])
  );
  DFF _128_ (
    .C(clk),
    .D(_001_[4]),
    .Q(dataout1[4])
  );
  DFF _129_ (
    .C(clk),
    .D(_001_[5]),
    .Q(dataout1[5])
  );
  DFF _130_ (
    .C(clk),
    .D(_002_),
    .Q(valid_0)
  );
  DFF _131_ (
    .C(clk),
    .D(_003_),
    .Q(valid_1)
  );
endmodule

LogicaMasterPrueba/demux.v
//IE-0523 Circuitos Digitales II
//Proyecto2. demux.
//Elaborado por: César Valverde Zuñiga	A86605
//I Ciclo 2019

// Este módulo genera las salidas dataout0 y dataout1, recibiendo como entrada datain a una frecuencia de f.

//`timescale 1ns/100ps

module demux(
							input clk,
							input reset_L,
							input valid_in,
							input [5:0] data_in,
							output reg [5:0] dataout0,
							output reg [5:0] dataout1,
							output reg valid_0,
        			output reg valid_1
);

        //Registros Internos
	reg selectorL1;

always @(*) begin
	if((!reset_L))begin
	selectorL1 <=0;
	end
	else begin
	selectorL1 <=data_in [5];
	end
end

	always @(posedge clk) begin
		if((!reset_L))begin
		dataout1<= 0;
		dataout0 <= 0;
		valid_0 <= 0;
    valid_1 <= 0;

		end
		else if (~valid_in)begin
				if (valid_0==0)begin
				dataout0 <= 0;
				end
				else begin
				valid_0 <= 0;
				end
				if (valid_1==0)begin
				dataout1 <= 0;
				end
				else if (valid_1==1)begin
				valid_1 <= 0;
				end
			end
		else if(valid_in)begin
				if(selectorL1)begin
					dataout1 <= data_in;
					valid_1 <=1;
					valid_0 <=0;

				end
				else begin
					dataout0 <= data_in;
					valid_0 <= 1;
					valid_1 <=0;
				end
		end
	  end

endmodule

Demux/Demux/demux_BancoDePruebas.v
//IE-0523 Circuitos Digitales II
//Proyecto2. Módulo Test_bench del Demux.
//Elaborado por el estudiante: César Valverde Zuñiga	A86605
//I Ciclo 2019

`timescale 1ns / 100ps
`include "demux.v"
`include "probador.v"
`include "demuxEstructural.v"
`include "cmos_cells.v"

module Test_Bench;

	wire reset_L, clk, valid_in, valid_0, valid_1;
	wire [5:0] dataout0, dataout1, data_in;

	//Instancia del módulo Demux Conductual
	demux DM(
				.clk 	(clk),
				.reset_L(reset_L),
				.valid_in(valid_in),
				.valid_0(valid_0),
				.valid_1(valid_1),
				.data_in (data_in),
				.dataout0 (dataout0),
				.dataout1 (dataout1)
	);

	//Instancia del módulo Demux Estrutural
	demuxEstructural DMEstr(
				.clk 	(clk),
				.reset_L(reset_L),
				.valid_in(valid_in),
				.valid_0(valid_0),
				.valid_1(valid_1),
				.data_in (data_in),
				.dataout0 (dataout0),
				.dataout1 (dataout1)
	);

	//Instancia del Probador Demux
	probador PDMux(	.clk (clk),
				.valid_0(valid_0),
				.valid_1(valid_1),
					.reset_L (reset_L),
					.valid_in(valid_in),
					.dataout0 (dataout0),
					.dataout1 (dataout1),
					.data_in (data_in)
	);


endmodule

Memoria/cmos_cells.v

module BUF(A, Y);
input A;
output Y;
assign Y = A;
endmodule

module NOT(A, Y);
input A;
output Y;
assign Y = ~A;
endmodule

module NAND(A, B, Y);
input A, B;
output Y;
assign Y = ~(A & B);
endmodule

module NOR(A, B, Y);
input A, B;
output Y;
assign Y = ~(A | B);
endmodule

module DFF(C, D, Q);
input C, D;
output reg Q;
always @(posedge C)
	Q <= D;
endmodule

module DFFSR(C, D, Q, S, R);
input C, D, S, R;
output reg Q;
always @(posedge C, posedge S, posedge R)
	if (S)
		Q <= 1'b1;
	else if (R)
		Q <= 1'b0;
	else
		Q <= D;
endmodule

Demux/Demux/demux.vcd
$date
	Wed Jul  3 14:22:49 2019
$end
$version
	Icarus Verilog
$end
$timescale
	100ps
$end
$scope module BUF $end
$var wire 1 ! A $end
$var wire 1 " Y $end
$upscope $end
$scope module DFFSR $end
$var wire 1 # C $end
$var wire 1 $ D $end
$var wire 1 % R $end
$var wire 1 & S $end
$var reg 1 ' Q $end
$upscope $end
$scope module Test_Bench $end
$var wire 6 ( dataout0 [5:0] $end
$var wire 6 ) dataout1 [5:0] $end
$var wire 1 * valid_0 $end
$var wire 1 + valid_1 $end
$var wire 1 , valid_in $end
$var wire 1 - reset_L $end
$var wire 6 . data_in [5:0] $end
$var wire 1 / clk $end
$scope module DM $end
$var wire 1 , valid_in $end
$var wire 1 - reset_L $end
$var wire 6 0 data_in [5:0] $end
$var wire 1 / clk $end
$var reg 6 1 dataout0 [5:0] $end
$var reg 6 2 dataout1 [5:0] $end
$var reg 1 3 selectorL1 $end
$var reg 1 4 valid_0 $end
$var reg 1 5 valid_1 $end
$upscope $end
$scope module DMEstr $end
$var wire 6 6 dataout0 [5:0] $end
$var wire 6 7 dataout1 [5:0] $end
$var wire 1 * valid_0 $end
$var wire 1 + valid_1 $end
$var wire 1 , valid_in $end
$var wire 1 - reset_L $end
$var wire 6 8 data_in [5:0] $end
$var wire 1 / clk $end
$var wire 1 9 _053_ $end
$var wire 1 : _052_ $end
$var wire 1 ; _051_ $end
$var wire 1 < _050_ $end
$var wire 1 = _049_ $end
$var wire 1 > _048_ $end
$var wire 1 ? _047_ $end
$var wire 1 @ _046_ $end
$var wire 1 A _045_ $end
$var wire 1 B _044_ $end
$var wire 1 C _043_ $end
$var wire 1 D _042_ $end
$var wire 1 E _041_ $end
$var wire 1 F _040_ $end
$var wire 1 G _039_ $end
$var wire 1 H _038_ $end
$var wire 1 I _037_ $end
$var wire 1 J _036_ $end
$var wire 1 K _035_ $end
$var wire 1 L _034_ $end
$var wire 1 M _033_ $end
$var wire 1 N _032_ $end
$var wire 1 O _031_ $end
$var wire 1 P _030_ $end
$var wire 1 Q _029_ $end
$var wire 1 R _028_ $end
$var wire 1 S _027_ $end
$var wire 1 T _026_ $end
$var wire 1 U _025_ $end
$var wire 1 V _024_ $end
$var wire 1 W _023_ $end
$var wire 1 X _022_ $end
$var wire 1 Y _021_ $end
$var wire 1 Z _020_ $end
$var wire 1 [ _019_ $end
$var wire 1 \ _018_ $end
$var wire 1 ] _017_ $end
$var wire 1 ^ _016_ $end
$var wire 1 _ _015_ $end
$var wire 1 ` _014_ $end
$var wire 1 a _013_ $end
$var wire 1 b _012_ $end
$var wire 1 c _011_ $end
$var wire 1 d _010_ $end
$var wire 1 e _009_ $end
$var wire 1 f _008_ $end
$var wire 1 g _007_ $end
$var wire 1 h _006_ $end
$var wire 1 i _005_ $end
$var wire 1 j _004_ $end
$var wire 1 k _003_ $end
$var wire 1 l _002_ $end
$var wire 6 m _001_ [5:0] $end
$var wire 6 n _000_ [5:0] $end
$scope module _054_ $end
$var wire 1 o A $end
$var wire 1 j Y $end
$upscope $end
$scope module _055_ $end
$var wire 1 i Y $end
$var wire 1 - B $end
$var wire 1 , A $end
$upscope $end
$scope module _056_ $end
$var wire 1 i A $end
$var wire 1 j B $end
$var wire 1 k Y $end
$upscope $end
$scope module _057_ $end
$var wire 1 i A $end
$var wire 1 p B $end
$var wire 1 l Y $end
$upscope $end
$scope module _058_ $end
$var wire 1 + A $end
$var wire 1 h Y $end
$var wire 1 , B $end
$upscope $end
$scope module _059_ $end
$var wire 1 h A $end
$var wire 1 k B $end
$var wire 1 g Y $end
$upscope $end
$scope module _060_ $end
$var wire 1 f Y $end
$var wire 1 - A $end
$upscope $end
$scope module _061_ $end
$var wire 1 q A $end
$var wire 1 e Y $end
$upscope $end
$scope module _062_ $end
$var wire 1 e A $end
$var wire 1 f B $end
$var wire 1 d Y $end
$upscope $end
$scope module _063_ $end
$var wire 1 d A $end
$var wire 1 g B $end
$var wire 1 c Y $end
$upscope $end
$scope module _064_ $end
$var wire 1 k A $end
$var wire 1 r B $end
$var wire 1 b Y $end
$upscope $end
$scope module _065_ $end
$var wire 1 b A $end
$var wire 1 c B $end
$var wire 1 s Y $end
$upscope $end
$scope module _066_ $end
$var wire 1 t A $end
$var wire 1 a Y $end
$upscope $end
$scope module _067_ $end
$var wire 1 a A $end
$var wire 1 f B $end
$var wire 1 ` Y $end
$upscope $end
$scope module _068_ $end
$var wire 1 ` A $end
$var wire 1 g B $end
$var wire 1 _ Y $end
$upscope $end
$scope module _069_ $end
$var wire 1 k A $end
$var wire 1 u B $end
$var wire 1 ^ Y $end
$upscope $end
$scope module _070_ $end
$var wire 1 ^ A $end
$var wire 1 _ B $end
$var wire 1 v Y $end
$upscope $end
$scope module _071_ $end
$var wire 1 w A $end
$var wire 1 ] Y $end
$upscope $end
$scope module _072_ $end
$var wire 1 ] A $end
$var wire 1 f B $end
$var wire 1 \ Y $end
$upscope $end
$scope module _073_ $end
$var wire 1 \ A $end
$var wire 1 g B $end
$var wire 1 [ Y $end
$upscope $end
$scope module _074_ $end
$var wire 1 k A $end
$var wire 1 x B $end
$var wire 1 Z Y $end
$upscope $end
$scope module _075_ $end
$var wire 1 Z A $end
$var wire 1 [ B $end
$var wire 1 y Y $end
$upscope $end
$scope module _076_ $end
$var wire 1 z A $end
$var wire 1 Y Y $end
$upscope $end
$scope module _077_ $end
$var wire 1 Y A $end
$var wire 1 f B $end
$var wire 1 X Y $end
$upscope $end
$scope module _078_ $end
$var wire 1 X A $end
$var wire 1 g B $end
$var wire 1 W Y $end
$upscope $end
$scope module _079_ $end
$var wire 1 k A $end
$var wire 1 { B $end
$var wire 1 V Y $end
$upscope $end
$scope module _080_ $end
$var wire 1 V A $end
$var wire 1 W B $end
$var wire 1 | Y $end
$upscope $end
$scope module _081_ $end
$var wire 1 } A $end
$var wire 1 U Y $end
$upscope $end
$scope module _082_ $end
$var wire 1 U A $end
$var wire 1 f B $end
$var wire 1 T Y $end
$upscope $end
$scope module _083_ $end
$var wire 1 T A $end
$var wire 1 g B $end
$var wire 1 S Y $end
$upscope $end
$scope module _084_ $end
$var wire 1 k A $end
$var wire 1 ~ B $end
$var wire 1 R Y $end
$upscope $end
$scope module _085_ $end
$var wire 1 R A $end
$var wire 1 S B $end
$var wire 1 !" Y $end
$upscope $end
$scope module _086_ $end
$var wire 1 Q Y $end
$var wire 1 , A $end
$upscope $end
$scope module _087_ $end
$var wire 1 Q A $end
$var wire 1 f B $end
$var wire 1 P Y $end
$upscope $end
$scope module _088_ $end
$var wire 1 P A $end
$var wire 1 "" B $end
$var wire 1 O Y $end
$upscope $end
$scope module _089_ $end
$var wire 1 h A $end
$var wire 1 N Y $end
$upscope $end
$scope module _090_ $end
$var wire 1 #" A $end
$var wire 1 M Y $end
$upscope $end
$scope module _091_ $end
$var wire 1 M A $end
$var wire 1 f B $end
$var wire 1 L Y $end
$upscope $end
$scope module _092_ $end
$var wire 1 L A $end
$var wire 1 N B $end
$var wire 1 K Y $end
$upscope $end
$scope module _093_ $end
$var wire 1 K A $end
$var wire 1 O B $end
$var wire 1 $" Y $end
$upscope $end
$scope module _094_ $end
$var wire 1 l A $end
$var wire 1 %" B $end
$var wire 1 J Y $end
$upscope $end
$scope module _095_ $end
$var wire 1 f B $end
$var wire 1 I Y $end
$var wire 1 , A $end
$upscope $end
$scope module _096_ $end
$var wire 1 I A $end
$var wire 1 * B $end
$var wire 1 H Y $end
$upscope $end
$scope module _097_ $end
$var wire 1 H A $end
$var wire 1 O B $end
$var wire 1 G Y $end
$upscope $end
$scope module _098_ $end
$var wire 1 G A $end
$var wire 1 &" B $end
$var wire 1 F Y $end
$upscope $end
$scope module _099_ $end
$var wire 1 F A $end
$var wire 1 J B $end
$var wire 1 '" Y $end
$upscope $end
$scope module _100_ $end
$var wire 1 l A $end
$var wire 1 (" B $end
$var wire 1 E Y $end
$upscope $end
$scope module _101_ $end
$var wire 1 G A $end
$var wire 1 )" B $end
$var wire 1 D Y $end
$upscope $end
$scope module _102_ $end
$var wire 1 D A $end
$var wire 1 E B $end
$var wire 1 *" Y $end
$upscope $end
$scope module _103_ $end
$var wire 1 l A $end
$var wire 1 +" B $end
$var wire 1 C Y $end
$upscope $end
$scope module _104_ $end
$var wire 1 G A $end
$var wire 1 ," B $end
$var wire 1 B Y $end
$upscope $end
$scope module _105_ $end
$var wire 1 B A $end
$var wire 1 C B $end
$var wire 1 -" Y $end
$upscope $end
$scope module _106_ $end
$var wire 1 l A $end
$var wire 1 ." B $end
$var wire 1 A Y $end
$upscope $end
$scope module _107_ $end
$var wire 1 G A $end
$var wire 1 /" B $end
$var wire 1 @ Y $end
$upscope $end
$scope module _108_ $end
$var wire 1 @ A $end
$var wire 1 A B $end
$var wire 1 0" Y $end
$upscope $end
$scope module _109_ $end
$var wire 1 l A $end
$var wire 1 1" B $end
$var wire 1 ? Y $end
$upscope $end
$scope module _110_ $end
$var wire 1 G A $end
$var wire 1 2" B $end
$var wire 1 > Y $end
$upscope $end
$scope module _111_ $end
$var wire 1 > A $end
$var wire 1 ? B $end
$var wire 1 3" Y $end
$upscope $end
$scope module _112_ $end
$var wire 1 4" A $end
$var wire 1 = Y $end
$upscope $end
$scope module _113_ $end
$var wire 1 * A $end
$var wire 1 < Y $end
$upscope $end
$scope module _114_ $end
$var wire 1 Q A $end
$var wire 1 ; Y $end
$var wire 1 - B $end
$upscope $end
$scope module _115_ $end
$var wire 1 ; A $end
$var wire 1 < B $end
$var wire 1 : Y $end
$upscope $end
$scope module _116_ $end
$var wire 1 : A $end
$var wire 1 k B $end
$var wire 1 9 Y $end
$upscope $end
$scope module _117_ $end
$var wire 1 9 A $end
$var wire 1 = B $end
$var wire 1 5" Y $end
$upscope $end
$scope module _118_ $end
$var wire 1 6" D $end
$var wire 1 / C $end
$var reg 1 7" Q $end
$upscope $end
$scope module _119_ $end
$var wire 1 8" D $end
$var wire 1 / C $end
$var reg 1 9" Q $end
$upscope $end
$scope module _120_ $end
$var wire 1 :" D $end
$var wire 1 / C $end
$var reg 1 ;" Q $end
$upscope $end
$scope module _121_ $end
$var wire 1 <" D $end
$var wire 1 / C $end
$var reg 1 =" Q $end
$upscope $end
$scope module _122_ $end
$var wire 1 >" D $end
$var wire 1 / C $end
$var reg 1 ?" Q $end
$upscope $end
$scope module _123_ $end
$var wire 1 @" D $end
$var wire 1 / C $end
$var reg 1 A" Q $end
$upscope $end
$scope module _124_ $end
$var wire 1 B" D $end
$var wire 1 / C $end
$var reg 1 C" Q $end
$upscope $end
$scope module _125_ $end
$var wire 1 D" D $end
$var wire 1 / C $end
$var reg 1 E" Q $end
$upscope $end
$scope module _126_ $end
$var wire 1 F" D $end
$var wire 1 / C $end
$var reg 1 G" Q $end
$upscope $end
$scope module _127_ $end
$var wire 1 H" D $end
$var wire 1 / C $end
$var reg 1 I" Q $end
$upscope $end
$scope module _128_ $end
$var wire 1 J" D $end
$var wire 1 / C $end
$var reg 1 K" Q $end
$upscope $end
$scope module _129_ $end
$var wire 1 L" D $end
$var wire 1 / C $end
$var reg 1 M" Q $end
$upscope $end
$scope module _130_ $end
$var wire 1 l D $end
$var wire 1 / C $end
$var reg 1 N" Q $end
$upscope $end
$scope module _131_ $end
$var wire 1 k D $end
$var wire 1 / C $end
$var reg 1 O" Q $end
$upscope $end
$upscope $end
$scope module PDMux $end
$var wire 6 P" dataout0 [5:0] $end
$var wire 6 Q" dataout1 [5:0] $end
$var wire 1 * valid_0 $end
$var wire 1 + valid_1 $end
$var reg 1 / clk $end
$var reg 6 R" data_in [5:0] $end
$var reg 1 - reset_L $end
$var reg 1 , valid_in $end
$upscope $end
$upscope $end
$enddefinitions $end
#0
$dumpvars
bx R"
bx Q"
bx P"
xO"
xN"
xM"
0L"
xK"
0J"
xI"
0H"
xG"
0F"
xE"
0D"
xC"
0B"
xA"
0@"
x?"
0>"
x="
0<"
x;"
0:"
x9"
08"
x7"
06"
05"
x4"
03"
x2"
x1"
00"
x/"
x."
0-"
x,"
x+"
0*"
x)"
x("
0'"
x&"
x%"
0$"
x#"
x""
0!"
x~
x}
0|
x{
xz
0y
xx
xw
0v
xu
xt
0s
xr
xq
xp
xo
b0 n
b0 m
0l
0k
xj
1i
xh
xg
1f
xe
0d
1c
1b
xa
0`
1_
1^
x]
0\
1[
1Z
xY
0X
1W
1V
xU
0T
1S
1R
xQ
0P
1O
xN
xM
0L
1K
1J
0I
1H
0G
1F
1E
1D
1C
1B
1A
1@
1?
1>
x=
x<
1;
0:
19
bx 8
bx 7
bx 6
x5
x4
03
bx 2
bx 1
bx 0
0/
bx .
0-
x,
x+
x*
bx )
bx (
x'
z&
z%
z$
z#
z"
z!
$end
#20
13
0g
0d
0`
0\
0X
0T
0L
1I
0N
1=
1e
1a
1]
1Y
1U
1M
0;
1h
0j
1<
0&"
0)"
0,"
0/"
02"
04"
0q
0t
0w
0z
0}
0#"
0f
1Q
11"
0."
1+"
0("
0%"
1""
1~
0{
1x
0u
0r
1p
1o
0+
05
0*
04
b0 (
b0 6
b0 P"
b0 1
b0 )
b0 7
b0 Q"
b0 2
07"
09"
0;"
0="
0?"
0A"
0C"
0E"
0G"
0I"
0K"
0M"
0N"
0O"
1-
0,
b110100 .
b110100 0
b110100 8
b110100 R"
1/
#40
0/
#60
1D"
1J"
1L"
1v
1!"
b110010 m
1$"
1G
0^
0R
09
0O
0g
1k
1P
1;
1N
0I
0h
0i
0Q
0+"
1("
0x
1u
1,
b110010 .
b110010 0
b110010 8
b110010 R"
1/
#80
0/
#100
0K
1F"
1B"
1y
b110111 m
1s
1`
1T
1L
0Z
0b
0a
0U
0M
1t
1}
1#"
1+"
1%"
1x
1r
15
b110010 2
1E"
1K"
b110010 )
b110010 7
b110010 Q"
1M"
1+
1O"
b110111 .
b110111 0
b110111 8
b110111 R"
1/
#120
0/
#140
1D"
1F"
1J"
0c
0_
0[
0S
1v
1y
1!"
0G
1g
1^
1Z
1R
19
0H"
1B"
1O
0|
b110111 m
1s
0k
1d
1\
0P
0;
1V
1b
1I
1i
0e
0]
1Q
1."
0%"
1{
0r
1q
1w
0,
b111110 .
b111110 0
b111110 8
b111110 R"
1G"
1C"
b110111 )
b110111 7
b110111 Q"
b110111 2
1/
#160
0/
#180
0B"
0D"
0F"
0J"
0s
0v
0y
0!"
0L"
b0 m
0$"
1c
1_
1[
1S
1K
0g
0N
1h
01"
0("
1%"
0~
0u
1r
05
0+
0O"
b101101 .
b101101 0
b101101 8
b101101 R"
1/
#200
0/
#220
03
18"
1>"
1*"
b10010 n
13"
0E
0?
1g
1l
0d
0`
0\
0T
0L
1P
1;
1N
0I
0h
0i
1j
1e
1a
1]
1U
1M
0Q
11"
0."
0+"
1("
0%"
0""
1~
0{
0x
1u
0r
0p
0o
0q
0t
0w
0}
0#"
1,
b10010 .
b10010 0
b10010 8
b10010 R"
0M"
0K"
0G"
0E"
0C"
b0 )
b0 7
b0 Q"
b0 2
1/
#240
0/
#260
16"
b10011 n
1'"
0J
1)"
12"
0<
1%"
1r
14
b10010 1
19"
b10010 (
b10010 6
b10010 P"
1?"
1*
1N"
b10011 .
b10011 0
b10011 8
b10011 R"
1/
#280
0/
#300
06"
08"
0>"
0'"
0*"
b0 n
03"
1J
1E
1?
0l
0P
1i
1f
1&"
0-
17"
b10011 (
b10011 6
b10011 P"
b10011 1
1/
#320
0/
#340
16"
18"
1>"
1'"
1*"
b10011 n
13"
0J
0E
0?
1l
1P
0i
0&"
0)"
02"
1<
0f
04
b0 1
07"
09"
b0 (
b0 6
b0 P"
0?"
0*
0N"
1-
1/
#360
0/
#380
13
1B"
1D"
16"
18"
1s
1v
0F
0D
0>
1'"
1*"
1>"
1L"
0g
0b
0^
09
b10011 n
13"
b100011 m
1$"
1G
1J
1E
1k
1?
0O
0l
0j
01"
1""
0~
1p
1o
0<
1&"
1)"
12"
b100011 .
b100011 0
b100011 8
b100011 R"
1N"
1?"
19"
17"
1*
14
b10011 (
b10011 6
b10011 P"
b10011 1
1/
#400
0/
#420
03
06"
08"
0>"
0'"
0*"
03"
1:"
0c
0_
1F
1D
1>
b100 n
1-"
0K
1L"
0F"
1D"
1B"
1g
19
1$"
0G
0y
1v
b100011 m
1s
0C
1d
1`
1L
0k
1O
1Z
1^
1b
1l
0e
0a
0M
1j
1q
1t
1#"
1<
1+"
0("
0%"
0""
1x
0u
0r
0p
0o
04
15
b100011 2
1C"
1E"
b100011 )
b100011 7
b100011 Q"
1M"
0*
0N"
1+
1O"
b100 .
b100 0
b100 8
b100 R"
1/
#440
0/
#460
13
0B"
0D"
1:"
0s
0v
0L"
09
0B
1-"
b0 m
0$"
06"
1c
1_
1:
b100 n
0'"
1G
1C
1K
0H
0g
0P
0;
1J
1O
0l
0N
1I
1i
0j
1h
1Q
1%"
1""
1r
1p
1o
0<
0&"
0)"
1,"
02"
0,
b100101 .
b100101 0
b100101 8
b100101 R"
0O"
1N"
0?"
1;"
09"
07"
0+
05
1*
14
b100 (
b100 6
b100 P"
b100 1
1/
#480
0/
#500
0:"
b0 n
0-"
1B
19
0d
0`
0L
0G
0:
1e
1a
1M
1H
0q
0t
0#"
1<
b0 2
04
0C"
0E"
b0 )
b0 7
b0 Q"
0M"
0*
0N"
1/
#520
0/
#540
0,"
0;"
b0 (
b0 6
b0 P"
b0 1
1/
