Demux/Demux_VC0_VC1/probador.v
module probador(		    		input valid_0,
						input valid_1,
						input wire [5:0] dataout0,
						input wire [5:0] dataout1,
						output reg reset_L,
						output reg clk,
						output reg valid_in,
						output reg [5:0] data_in
						);

initial clk <=0;
always begin
	#2 clk <= ~clk;
end

initial begin
	$dumpfile("demux.vcd");
	$dumpvars;

	reset_L <= 1'b0;
	@(posedge clk)
	data_in<=6'h34;
	valid_in<=0;
	reset_L <= 1'b1;

	@(posedge clk)
	data_in <= 6'h32;
	valid_in<=1;

	@(posedge clk)
	data_in <= 6'h37;
	valid_in<=1;

	@(posedge clk)
	data_in <= 6'h7E;
	valid_in<=0;

	@(posedge clk)
	data_in <= 6'h2D;
	valid_in<=0;

	@(posedge clk)
	data_in <= 6'h12;
	valid_in<=1;

	@(posedge clk)
	data_in <= 6'h13;
	valid_in<=1;

	@(posedge clk)
	reset_L <= 1'b0;

	@(posedge clk)
	reset_L <= 1'b1;

	@(posedge clk)
	data_in <= 6'h23;
	valid_in<=1;

	@(posedge clk)
	data_in <= 6'h4;
	valid_in<=1;

	@(posedge clk)
	data_in <= 6'h25;
	valid_in<=0;

	#30 $finish;
end

endmodule

Demux/Demux_VC0_VC1/demuxEstructural.v
/* Generated by Yosys 0.7 (git sha1 61f6811, gcc 6.2.0-11ubuntu1 -O2 -fdebug-prefix-map=/build/yosys-OIL3SR/yosys-0.7=. -fstack-protector-strong -fPIC -Os) */

module demuxEstructural(clk, reset_L, valid_in, data_in, dataout0, dataout1, valid_0, valid_1);
  wire [5:0] _00_;
  wire [5:0] _01_;
  wire _02_;
  wire _03_;
  wire _04_;
  wire _05_;
  wire _06_;
  wire _07_;
  wire _08_;
  wire _09_;
  wire _10_;
  wire _11_;
  wire _12_;
  wire _13_;
  wire _14_;
  wire _15_;
  wire _16_;
  wire _17_;
  wire _18_;
  wire _19_;
  wire _20_;
  wire _21_;
  wire _22_;
  wire _23_;
  wire _24_;
  wire _25_;
  wire _26_;
  wire _27_;
  wire _28_;
  wire _29_;
  wire _30_;
  wire _31_;
  input clk;
  input [5:0] data_in;
  output [5:0] dataout0;
  output [5:0] dataout1;
  input reset_L;
  output valid_0;
  output valid_1;
  input valid_in;
  NAND _32_ (
    .A(reset_L),
    .B(valid_in),
    .Y(_04_)
  );
  NOR _33_ (
    .A(_04_),
    .B(data_in[5]),
    .Y(_02_)
  );
  NAND _34_ (
    .A(_02_),
    .B(dataout1[0]),
    .Y(_05_)
  );
  NOT _35_ (
    .A(data_in[5]),
    .Y(_06_)
  );
  NOR _36_ (
    .A(_04_),
    .B(_06_),
    .Y(_03_)
  );
  NAND _37_ (
    .A(_03_),
    .B(data_in[0]),
    .Y(_07_)
  );
  NAND _38_ (
    .A(_07_),
    .B(_05_),
    .Y(_01_[0])
  );
  NAND _39_ (
    .A(_02_),
    .B(dataout1[1]),
    .Y(_08_)
  );
  NAND _40_ (
    .A(_03_),
    .B(data_in[1]),
    .Y(_09_)
  );
  NAND _41_ (
    .A(_09_),
    .B(_08_),
    .Y(_01_[1])
  );
  NAND _42_ (
    .A(_02_),
    .B(dataout1[2]),
    .Y(_10_)
  );
  NAND _43_ (
    .A(_03_),
    .B(data_in[2]),
    .Y(_11_)
  );
  NAND _44_ (
    .A(_11_),
    .B(_10_),
    .Y(_01_[2])
  );
  NAND _45_ (
    .A(_02_),
    .B(dataout1[3]),
    .Y(_12_)
  );
  NAND _46_ (
    .A(_03_),
    .B(data_in[3]),
    .Y(_13_)
  );
  NAND _47_ (
    .A(_13_),
    .B(_12_),
    .Y(_01_[3])
  );
  NAND _48_ (
    .A(_02_),
    .B(dataout1[4]),
    .Y(_14_)
  );
  NAND _49_ (
    .A(_03_),
    .B(data_in[4]),
    .Y(_15_)
  );
  NAND _50_ (
    .A(_15_),
    .B(_14_),
    .Y(_01_[4])
  );
  NOR _51_ (
    .A(data_in[5]),
    .B(dataout1[5]),
    .Y(_16_)
  );
  NOR _52_ (
    .A(_16_),
    .B(_04_),
    .Y(_01_[5])
  );
  NAND _53_ (
    .A(_02_),
    .B(data_in[0]),
    .Y(_17_)
  );
  NAND _54_ (
    .A(_03_),
    .B(dataout0[0]),
    .Y(_18_)
  );
  NAND _55_ (
    .A(_18_),
    .B(_17_),
    .Y(_00_[0])
  );
  NAND _56_ (
    .A(_02_),
    .B(data_in[1]),
    .Y(_19_)
  );
  NAND _57_ (
    .A(_03_),
    .B(dataout0[1]),
    .Y(_20_)
  );
  NAND _58_ (
    .A(_20_),
    .B(_19_),
    .Y(_00_[1])
  );
  NAND _59_ (
    .A(_02_),
    .B(data_in[2]),
    .Y(_21_)
  );
  NAND _60_ (
    .A(_03_),
    .B(dataout0[2]),
    .Y(_22_)
  );
  NAND _61_ (
    .A(_22_),
    .B(_21_),
    .Y(_00_[2])
  );
  NAND _62_ (
    .A(_02_),
    .B(data_in[3]),
    .Y(_23_)
  );
  NAND _63_ (
    .A(_03_),
    .B(dataout0[3]),
    .Y(_24_)
  );
  NAND _64_ (
    .A(_24_),
    .B(_23_),
    .Y(_00_[3])
  );
  NAND _65_ (
    .A(_02_),
    .B(data_in[4]),
    .Y(_25_)
  );
  NAND _66_ (
    .A(_03_),
    .B(dataout0[4]),
    .Y(_26_)
  );
  NAND _67_ (
    .A(_26_),
    .B(_25_),
    .Y(_00_[4])
  );
  NOT _68_ (
    .A(dataout0[5]),
    .Y(_27_)
  );
  NOT _69_ (
    .A(valid_in),
    .Y(_28_)
  );
  NOT _70_ (
    .A(reset_L),
    .Y(_29_)
  );
  NOR _71_ (
    .A(_29_),
    .B(_28_),
    .Y(_30_)
  );
  NAND _72_ (
    .A(_30_),
    .B(data_in[5]),
    .Y(_31_)
  );
  NOR _73_ (
    .A(_31_),
    .B(_27_),
    .Y(_00_[5])
  );
  DFF _74_ (
    .C(clk),
    .D(_00_[0]),
    .Q(dataout0[0])
  );
  DFF _75_ (
    .C(clk),
    .D(_00_[1]),
    .Q(dataout0[1])
  );
  DFF _76_ (
    .C(clk),
    .D(_00_[2]),
    .Q(dataout0[2])
  );
  DFF _77_ (
    .C(clk),
    .D(_00_[3]),
    .Q(dataout0[3])
  );
  DFF _78_ (
    .C(clk),
    .D(_00_[4]),
    .Q(dataout0[4])
  );
  DFF _79_ (
    .C(clk),
    .D(_00_[5]),
    .Q(dataout0[5])
  );
  DFF _80_ (
    .C(clk),
    .D(_01_[0]),
    .Q(dataout1[0])
  );
  DFF _81_ (
    .C(clk),
    .D(_01_[1]),
    .Q(dataout1[1])
  );
  DFF _82_ (
    .C(clk),
    .D(_01_[2]),
    .Q(dataout1[2])
  );
  DFF _83_ (
    .C(clk),
    .D(_01_[3]),
    .Q(dataout1[3])
  );
  DFF _84_ (
    .C(clk),
    .D(_01_[4]),
    .Q(dataout1[4])
  );
  DFF _85_ (
    .C(clk),
    .D(_01_[5]),
    .Q(dataout1[5])
  );
  DFF _86_ (
    .C(clk),
    .D(_02_),
    .Q(valid_0)
  );
  DFF _87_ (
    .C(clk),
    .D(_03_),
    .Q(valid_1)
  );
endmodule

LogicaMasterPrueba/demux.v
//IE-0523 Circuitos Digitales II
//Proyecto2. demux.
//Elaborado por: César Valverde Zuñiga	A86605
//I Ciclo 2019

// Este módulo genera las salidas dataout0 y dataout1, recibiendo como entrada datain a una frecuencia de f.

//`timescale 1ns/100ps

module demux(
							input clk,
							input reset_L,
							input valid_in,
							input [5:0] data_in,
							output reg [5:0] dataout0,
							output reg [5:0] dataout1,
							output reg valid_0,
        			output reg valid_1
);

        //Registros Internos
	reg selectorL1;

always @(*) begin
	if((!reset_L))begin
	selectorL1 <=0;
	end
	else begin
	selectorL1 <=data_in [5];
	end
end

	always @(posedge clk) begin
		if((!reset_L))begin
		dataout1<= 0;
		dataout0 <= 0;
		valid_0 <= 0;
    valid_1 <= 0;

		end
		else if (~valid_in)begin
				if (valid_0==0)begin
				dataout0 <= 0;
				end
				else begin
				valid_0 <= 0;
				end
				if (valid_1==0)begin
				dataout1 <= 0;
				end
				else if (valid_1==1)begin
				valid_1 <= 0;
				end
			end
		else if(valid_in)begin
				if(selectorL1)begin
					dataout1 <= data_in;
					valid_1 <=1;
					valid_0 <=0;

				end
				else begin
					dataout0 <= data_in;
					valid_0 <= 1;
					valid_1 <=0;
				end
		end
	  end

endmodule

Demux/Demux/demux_BancoDePruebas.v
//IE-0523 Circuitos Digitales II
//Proyecto2. Módulo Test_bench del Demux.
//Elaborado por el estudiante: César Valverde Zuñiga	A86605
//I Ciclo 2019

`timescale 1ns / 100ps
`include "demux.v"
`include "probador.v"
`include "demuxEstructural.v"
`include "cmos_cells.v"

module Test_Bench;

	wire reset_L, clk, valid_in, valid_0, valid_1;
	wire [5:0] dataout0, dataout1, data_in;

	//Instancia del módulo Demux Conductual
	demux DM(
				.clk 	(clk),
				.reset_L(reset_L),
				.valid_in(valid_in),
				.valid_0(valid_0),
				.valid_1(valid_1),
				.data_in (data_in),
				.dataout0 (dataout0),
				.dataout1 (dataout1)
	);

	//Instancia del módulo Demux Estrutural
	demuxEstructural DMEstr(
				.clk 	(clk),
				.reset_L(reset_L),
				.valid_in(valid_in),
				.valid_0(valid_0),
				.valid_1(valid_1),
				.data_in (data_in),
				.dataout0 (dataout0),
				.dataout1 (dataout1)
	);

	//Instancia del Probador Demux
	probador PDMux(	.clk (clk),
				.valid_0(valid_0),
				.valid_1(valid_1),
					.reset_L (reset_L),
					.valid_in(valid_in),
					.dataout0 (dataout0),
					.dataout1 (dataout1),
					.data_in (data_in)
	);


endmodule

Memoria/cmos_cells.v

module BUF(A, Y);
input A;
output Y;
assign Y = A;
endmodule

module NOT(A, Y);
input A;
output Y;
assign Y = ~A;
endmodule

module NAND(A, B, Y);
input A, B;
output Y;
assign Y = ~(A & B);
endmodule

module NOR(A, B, Y);
input A, B;
output Y;
assign Y = ~(A | B);
endmodule

module DFF(C, D, Q);
input C, D;
output reg Q;
always @(posedge C)
	Q <= D;
endmodule

module DFFSR(C, D, Q, S, R);
input C, D, S, R;
output reg Q;
always @(posedge C, posedge S, posedge R)
	if (S)
		Q <= 1'b1;
	else if (R)
		Q <= 1'b0;
	else
		Q <= D;
endmodule

Demux/Demux_VC0_VC1/demux.vcd
$date
	Tue Jul  9 21:55:54 2019
$end
$version
	Icarus Verilog
$end
$timescale
	100ps
$end
$scope module BUF $end
$var wire 1 ! A $end
$var wire 1 " Y $end
$upscope $end
$scope module DFFSR $end
$var wire 1 # C $end
$var wire 1 $ D $end
$var wire 1 % R $end
$var wire 1 & S $end
$var reg 1 ' Q $end
$upscope $end
$scope module Test_Bench $end
$var wire 6 ( dataout0 [5:0] $end
$var wire 6 ) dataout1 [5:0] $end
$var wire 1 * valid_0 $end
$var wire 1 + valid_1 $end
$var wire 1 , valid_in $end
$var wire 1 - reset_L $end
$var wire 6 . data_in [5:0] $end
$var wire 1 / clk $end
$scope module DM $end
$var wire 1 , valid_in $end
$var wire 1 - reset_L $end
$var wire 6 0 data_in [5:0] $end
$var wire 1 / clk $end
$var reg 6 1 dataout0 [5:0] $end
$var reg 6 2 dataout1 [5:0] $end
$var reg 1 3 selectorL1 $end
$var reg 1 4 valid_0 $end
$var reg 1 5 valid_1 $end
$upscope $end
$scope module DMEstr $end
$var wire 6 6 dataout0 [5:0] $end
$var wire 6 7 dataout1 [5:0] $end
$var wire 1 * valid_0 $end
$var wire 1 + valid_1 $end
$var wire 1 , valid_in $end
$var wire 1 - reset_L $end
$var wire 6 8 data_in [5:0] $end
$var wire 1 / clk $end
$var wire 1 9 _31_ $end
$var wire 1 : _30_ $end
$var wire 1 ; _29_ $end
$var wire 1 < _28_ $end
$var wire 1 = _27_ $end
$var wire 1 > _26_ $end
$var wire 1 ? _25_ $end
$var wire 1 @ _24_ $end
$var wire 1 A _23_ $end
$var wire 1 B _22_ $end
$var wire 1 C _21_ $end
$var wire 1 D _20_ $end
$var wire 1 E _19_ $end
$var wire 1 F _18_ $end
$var wire 1 G _17_ $end
$var wire 1 H _16_ $end
$var wire 1 I _15_ $end
$var wire 1 J _14_ $end
$var wire 1 K _13_ $end
$var wire 1 L _12_ $end
$var wire 1 M _11_ $end
$var wire 1 N _10_ $end
$var wire 1 O _09_ $end
$var wire 1 P _08_ $end
$var wire 1 Q _07_ $end
$var wire 1 R _06_ $end
$var wire 1 S _05_ $end
$var wire 1 T _04_ $end
$var wire 1 U _03_ $end
$var wire 1 V _02_ $end
$var wire 6 W _01_ [5:0] $end
$var wire 6 X _00_ [5:0] $end
$scope module _32_ $end
$var wire 1 T Y $end
$var wire 1 , B $end
$var wire 1 - A $end
$upscope $end
$scope module _33_ $end
$var wire 1 T A $end
$var wire 1 Y B $end
$var wire 1 V Y $end
$upscope $end
$scope module _34_ $end
$var wire 1 V A $end
$var wire 1 Z B $end
$var wire 1 S Y $end
$upscope $end
$scope module _35_ $end
$var wire 1 [ A $end
$var wire 1 R Y $end
$upscope $end
$scope module _36_ $end
$var wire 1 T A $end
$var wire 1 R B $end
$var wire 1 U Y $end
$upscope $end
$scope module _37_ $end
$var wire 1 U A $end
$var wire 1 \ B $end
$var wire 1 Q Y $end
$upscope $end
$scope module _38_ $end
$var wire 1 Q A $end
$var wire 1 S B $end
$var wire 1 ] Y $end
$upscope $end
$scope module _39_ $end
$var wire 1 V A $end
$var wire 1 ^ B $end
$var wire 1 P Y $end
$upscope $end
$scope module _40_ $end
$var wire 1 U A $end
$var wire 1 _ B $end
$var wire 1 O Y $end
$upscope $end
$scope module _41_ $end
$var wire 1 O A $end
$var wire 1 P B $end
$var wire 1 ` Y $end
$upscope $end
$scope module _42_ $end
$var wire 1 V A $end
$var wire 1 a B $end
$var wire 1 N Y $end
$upscope $end
$scope module _43_ $end
$var wire 1 U A $end
$var wire 1 b B $end
$var wire 1 M Y $end
$upscope $end
$scope module _44_ $end
$var wire 1 M A $end
$var wire 1 N B $end
$var wire 1 c Y $end
$upscope $end
$scope module _45_ $end
$var wire 1 V A $end
$var wire 1 d B $end
$var wire 1 L Y $end
$upscope $end
$scope module _46_ $end
$var wire 1 U A $end
$var wire 1 e B $end
$var wire 1 K Y $end
$upscope $end
$scope module _47_ $end
$var wire 1 K A $end
$var wire 1 L B $end
$var wire 1 f Y $end
$upscope $end
$scope module _48_ $end
$var wire 1 V A $end
$var wire 1 g B $end
$var wire 1 J Y $end
$upscope $end
$scope module _49_ $end
$var wire 1 U A $end
$var wire 1 h B $end
$var wire 1 I Y $end
$upscope $end
$scope module _50_ $end
$var wire 1 I A $end
$var wire 1 J B $end
$var wire 1 i Y $end
$upscope $end
$scope module _51_ $end
$var wire 1 j A $end
$var wire 1 k B $end
$var wire 1 H Y $end
$upscope $end
$scope module _52_ $end
$var wire 1 H A $end
$var wire 1 T B $end
$var wire 1 l Y $end
$upscope $end
$scope module _53_ $end
$var wire 1 V A $end
$var wire 1 m B $end
$var wire 1 G Y $end
$upscope $end
$scope module _54_ $end
$var wire 1 U A $end
$var wire 1 n B $end
$var wire 1 F Y $end
$upscope $end
$scope module _55_ $end
$var wire 1 F A $end
$var wire 1 G B $end
$var wire 1 o Y $end
$upscope $end
$scope module _56_ $end
$var wire 1 V A $end
$var wire 1 p B $end
$var wire 1 E Y $end
$upscope $end
$scope module _57_ $end
$var wire 1 U A $end
$var wire 1 q B $end
$var wire 1 D Y $end
$upscope $end
$scope module _58_ $end
$var wire 1 D A $end
$var wire 1 E B $end
$var wire 1 r Y $end
$upscope $end
$scope module _59_ $end
$var wire 1 V A $end
$var wire 1 s B $end
$var wire 1 C Y $end
$upscope $end
$scope module _60_ $end
$var wire 1 U A $end
$var wire 1 t B $end
$var wire 1 B Y $end
$upscope $end
$scope module _61_ $end
$var wire 1 B A $end
$var wire 1 C B $end
$var wire 1 u Y $end
$upscope $end
$scope module _62_ $end
$var wire 1 V A $end
$var wire 1 v B $end
$var wire 1 A Y $end
$upscope $end
$scope module _63_ $end
$var wire 1 U A $end
$var wire 1 w B $end
$var wire 1 @ Y $end
$upscope $end
$scope module _64_ $end
$var wire 1 @ A $end
$var wire 1 A B $end
$var wire 1 x Y $end
$upscope $end
$scope module _65_ $end
$var wire 1 V A $end
$var wire 1 y B $end
$var wire 1 ? Y $end
$upscope $end
$scope module _66_ $end
$var wire 1 U A $end
$var wire 1 z B $end
$var wire 1 > Y $end
$upscope $end
$scope module _67_ $end
$var wire 1 > A $end
$var wire 1 ? B $end
$var wire 1 { Y $end
$upscope $end
$scope module _68_ $end
$var wire 1 | A $end
$var wire 1 = Y $end
$upscope $end
$scope module _69_ $end
$var wire 1 < Y $end
$var wire 1 , A $end
$upscope $end
$scope module _70_ $end
$var wire 1 ; Y $end
$var wire 1 - A $end
$upscope $end
$scope module _71_ $end
$var wire 1 ; A $end
$var wire 1 < B $end
$var wire 1 : Y $end
$upscope $end
$scope module _72_ $end
$var wire 1 : A $end
$var wire 1 } B $end
$var wire 1 9 Y $end
$upscope $end
$scope module _73_ $end
$var wire 1 9 A $end
$var wire 1 = B $end
$var wire 1 ~ Y $end
$upscope $end
$scope module _74_ $end
$var wire 1 !" D $end
$var wire 1 / C $end
$var reg 1 "" Q $end
$upscope $end
$scope module _75_ $end
$var wire 1 #" D $end
$var wire 1 / C $end
$var reg 1 $" Q $end
$upscope $end
$scope module _76_ $end
$var wire 1 %" D $end
$var wire 1 / C $end
$var reg 1 &" Q $end
$upscope $end
$scope module _77_ $end
$var wire 1 '" D $end
$var wire 1 / C $end
$var reg 1 (" Q $end
$upscope $end
$scope module _78_ $end
$var wire 1 )" D $end
$var wire 1 / C $end
$var reg 1 *" Q $end
$upscope $end
$scope module _79_ $end
$var wire 1 +" D $end
$var wire 1 / C $end
$var reg 1 ," Q $end
$upscope $end
$scope module _80_ $end
$var wire 1 -" D $end
$var wire 1 / C $end
$var reg 1 ." Q $end
$upscope $end
$scope module _81_ $end
$var wire 1 /" D $end
$var wire 1 / C $end
$var reg 1 0" Q $end
$upscope $end
$scope module _82_ $end
$var wire 1 1" D $end
$var wire 1 / C $end
$var reg 1 2" Q $end
$upscope $end
$scope module _83_ $end
$var wire 1 3" D $end
$var wire 1 / C $end
$var reg 1 4" Q $end
$upscope $end
$scope module _84_ $end
$var wire 1 5" D $end
$var wire 1 / C $end
$var reg 1 6" Q $end
$upscope $end
$scope module _85_ $end
$var wire 1 7" D $end
$var wire 1 / C $end
$var reg 1 8" Q $end
$upscope $end
$scope module _86_ $end
$var wire 1 V D $end
$var wire 1 / C $end
$var reg 1 9" Q $end
$upscope $end
$scope module _87_ $end
$var wire 1 U D $end
$var wire 1 / C $end
$var reg 1 :" Q $end
$upscope $end
$upscope $end
$scope module PDMux $end
$var wire 6 ;" dataout0 [5:0] $end
$var wire 6 <" dataout1 [5:0] $end
$var wire 1 * valid_0 $end
$var wire 1 + valid_1 $end
$var reg 1 / clk $end
$var reg 6 =" data_in [5:0] $end
$var reg 1 - reset_L $end
$var reg 1 , valid_in $end
$upscope $end
$upscope $end
$enddefinitions $end
#0
$dumpvars
bx ="
bx <"
bx ;"
x:"
x9"
x8"
07"
x6"
05"
x4"
03"
x2"
01"
x0"
0/"
x."
0-"
x,"
0+"
x*"
0)"
x("
0'"
x&"
0%"
x$"
0#"
x""
0!"
0~
x}
x|
0{
xz
xy
0x
xw
xv
0u
xt
xs
0r
xq
xp
0o
xn
xm
0l
xk
xj
0i
xh
xg
0f
xe
xd
0c
xb
xa
0`
x_
x^
0]
x\
x[
xZ
xY
b0 X
b0 W
0V
0U
1T
1S
xR
1Q
1P
1O
1N
1M
1L
1K
1J
1I
xH
1G
1F
1E
1D
1C
1B
1A
1@
1?
1>
x=
x<
1;
0:
19
bx 8
bx 7
bx 6
x5
x4
03
bx 2
bx 1
bx 0
0/
bx .
0-
x,
x+
x*
bx )
bx (
x'
z&
z%
z$
z#
z"
z!
$end
#20
13
0H
1=
0R
0n
0q
0t
0w
0z
0|
0Z
0^
0a
0d
0g
0k
0;
1<
1}
1y
0v
1s
0p
0m
1j
1h
0e
1b
0_
0\
1[
1Y
0+
05
0*
04
b0 (
b0 6
b0 ;"
b0 1
b0 )
b0 7
b0 <"
b0 2
0""
0$"
0&"
0("
0*"
0,"
0."
00"
02"
04"
06"
08"
09"
0:"
1-
0,
b110100 .
b110100 0
b110100 8
b110100 ="
1/
#40
0/
#60
1/"
15"
1`
1i
0O
0I
09
17"
1U
b110010 W
1l
1:
0T
0<
0s
1p
0b
1_
1,
b110010 .
b110010 0
b110010 8
b110010 ="
1/
#80
0/
#100
11"
1-"
1c
b110111 W
1]
0M
0Q
1^
1g
1k
1s
1m
1b
1\
15
b110010 2
10"
16"
b110010 )
b110010 7
b110010 <"
18"
1+
1:"
b110111 .
b110111 0
b110111 8
b110111 ="
1/
#120
0/
#140
0/"
01"
05"
0`
0c
0i
1O
1M
1I
03"
0-"
19
07"
0f
0]
0U
b0 W
0l
0:
1K
1Q
1T
1<
1v
0m
1e
0\
1Z
1a
0,
b111110 .
b111110 0
b111110 8
b111110 ="
12"
1."
b110111 )
b110111 7
b110111 <"
b110111 2
1/
#160
0/
#180
0Z
0^
0a
0g
0k
0y
0p
1m
0h
0_
1\
05
b0 2
0."
00"
02"
06"
b0 )
b0 7
b0 <"
08"
0+
0:"
b101101 .
b101101 0
b101101 8
b101101 ="
1/
#200
0/
#220
03
1#"
1)"
1r
b10010 X
1{
0E
0?
1V
1:
1H
0T
1R
0<
0}
1y
0v
0s
1p
0m
0j
1h
0e
0b
1_
0\
0[
0Y
1,
b10010 .
b10010 0
b10010 8
b10010 ="
1/
#240
0/
#260
1!"
b10011 X
1o
0G
1q
1z
1m
1\
14
b10010 1
1$"
b10010 (
b10010 6
b10010 ;"
1*"
1*
19"
b10011 .
b10011 0
b10011 8
b10011 ="
1/
#280
0/
#300
0!"
0#"
0)"
0o
0r
b0 X
0{
1G
1E
1?
0V
0:
1T
1;
1n
0-
1""
b10011 (
b10011 6
b10011 ;"
b10011 1
1/
#320
0/
#340
1!"
1#"
1)"
1o
1r
b10011 X
1{
0G
0E
0?
1V
1:
0T
0n
0q
0z
0;
04
b0 1
0""
0$"
b0 (
b0 6
b0 ;"
0*"
0*
09"
1-
1/
#360
0/
#380
13
1-"
1/"
1]
1`
1!"
1#"
1o
1r
1)"
17"
0Q
0O
0F
0D
0>
b10011 X
1{
b100011 W
1l
1G
1E
1U
09
1?
0H
0V
0R
1}
0y
1j
0h
1[
1Y
1n
1q
1z
b100011 .
b100011 0
b100011 8
b100011 ="
19"
1*"
1$"
1""
1*
14
b10011 (
b10011 6
b10011 ;"
b10011 1
1/
#400
0/
#420
03
0!"
0#"
0)"
0o
0r
0{
1%"
b100 X
1u
01"
1/"
1-"
1F
1D
1>
0c
1`
b100011 W
1]
0S
0P
0C
0U
19
1M
1O
1Q
1V
1R
1Z
1^
1k
0}
1s
0p
0m
0j
1b
0_
0\
0[
0Y
04
15
b100011 2
1."
10"
b100011 )
b100011 7
b100011 <"
18"
0*
09"
1+
1:"
b100 .
b100 0
b100 8
b100 ="
1/
#440
0/
#460
13
0-"
0/"
0%"
0]
0`
0u
0!"
07"
b0 X
0o
1S
1P
1C
b0 W
0l
0:
19
1G
0V
1T
0R
1<
1}
1m
1j
1\
1[
1Y
0n
0q
1t
0z
0,
b100101 .
b100101 0
b100101 8
b100101 ="
0:"
19"
0*"
1&"
0$"
0""
0+
05
1*
14
b100 (
b100 6
b100 ;"
b100 1
1/
#480
0/
#500
0t
0Z
0^
0k
04
b0 1
b0 2
b0 (
b0 6
b0 ;"
0&"
0."
00"
b0 )
b0 7
b0 <"
08"
0*
09"
1/
