Demux/probador.v
module probador(		    		input valid_0,
						input valid_1,
						input wire [3:0] dataout0,
						input wire [3:0] dataout1,
						output reg reset_L, 
						output reg clk,
						output reg valid_in,
						output reg [3:0] data_in
						);

initial clk <=0;
always begin
	#2 clk <= ~clk;
end

initial begin
	$dumpfile("demux.vcd");
	$dumpvars;

	reset_L <= 1'b0;
	@(posedge clk)
	data_in<=4'b0;
	valid_in<=0;
	reset_L <= 1'b1;

	@(posedge clk)
	data_in <= 4'b1010;
	valid_in<=1;

	@(posedge clk)
	data_in <= 4'b1111;
	valid_in<=1;

	@(posedge clk)
	data_in <= 4'b1110;
	valid_in<=0;

	@(posedge clk)
	data_in <= 4'b1101;
	valid_in<=0;
	
	@(posedge clk)
	data_in <= 4'b0010;
	valid_in<=1;

	@(posedge clk)
	data_in <= 8'b10101011;
	valid_in<=1;

	@(posedge clk)
	data_in <= 4'b0011;
	valid_in<=1;

	@(posedge clk)
	data_in <= 4'b0100;
	valid_in<=1;
	
	@(posedge clk)
	data_in <= 4'b0101;
	valid_in<=0;

	#30 $finish;
end

endmodule

Demux/demuxEstructural.v
/* Generated by Yosys 0.7 (git sha1 61f6811, gcc 6.2.0-11ubuntu1 -O2 -fdebug-prefix-map=/build/yosys-zWLHjG/yosys-0.7=. -fstack-protector-strong -fPIC -Os) */

module demuxEstructural(clk, reset_L, valid_in, data_in, dataout0, dataout1, valid_0, valid_1);
  wire [3:0] _000_;
  wire [3:0] _001_;
  wire _002_;
  wire _003_;
  wire _004_;
  wire _005_;
  wire _006_;
  wire _007_;
  wire _008_;
  wire _009_;
  wire _010_;
  wire _011_;
  wire _012_;
  wire _013_;
  wire _014_;
  wire _015_;
  wire _016_;
  wire _017_;
  wire _018_;
  wire _019_;
  wire _020_;
  wire _021_;
  wire _022_;
  wire _023_;
  wire _024_;
  wire _025_;
  wire _026_;
  wire _027_;
  wire _028_;
  wire _029_;
  wire _030_;
  wire _031_;
  wire _032_;
  wire _033_;
  wire _034_;
  wire _035_;
  wire _036_;
  wire _037_;
  wire _038_;
  wire _039_;
  wire _040_;
  wire _041_;
  wire _042_;
  wire _043_;
  wire _044_;
  wire _045_;
  wire _046_;
  input clk;
  input [3:0] data_in;
  output [3:0] dataout0;
  output [3:0] dataout1;
  input reset_L;
  wire selectorL1;
  output valid_0;
  output valid_1;
  input valid_in;
  NOT _047_ (
    .A(reset_L),
    .Y(_005_)
  );
  NOT _048_ (
    .A(selectorL1),
    .Y(_006_)
  );
  NAND _049_ (
    .A(_006_),
    .B(valid_in),
    .Y(_007_)
  );
  NOR _050_ (
    .A(_007_),
    .B(_005_),
    .Y(_004_)
  );
  NAND _051_ (
    .A(selectorL1),
    .B(valid_in),
    .Y(_008_)
  );
  NOR _052_ (
    .A(_008_),
    .B(_005_),
    .Y(_003_)
  );
  NOT _053_ (
    .A(valid_in),
    .Y(_009_)
  );
  NAND _054_ (
    .A(valid_1),
    .B(_009_),
    .Y(_010_)
  );
  NAND _055_ (
    .A(_010_),
    .B(_008_),
    .Y(_011_)
  );
  NOT _056_ (
    .A(dataout1[0]),
    .Y(_012_)
  );
  NOR _057_ (
    .A(_012_),
    .B(_005_),
    .Y(_013_)
  );
  NAND _058_ (
    .A(_013_),
    .B(_011_),
    .Y(_014_)
  );
  NAND _059_ (
    .A(_004_),
    .B(data_in[0]),
    .Y(_015_)
  );
  NAND _060_ (
    .A(_015_),
    .B(_014_),
    .Y(_001_[0])
  );
  NOT _061_ (
    .A(dataout1[1]),
    .Y(_016_)
  );
  NOR _062_ (
    .A(_016_),
    .B(_005_),
    .Y(_017_)
  );
  NAND _063_ (
    .A(_017_),
    .B(_011_),
    .Y(_018_)
  );
  NAND _064_ (
    .A(_004_),
    .B(data_in[1]),
    .Y(_019_)
  );
  NAND _065_ (
    .A(_019_),
    .B(_018_),
    .Y(_001_[1])
  );
  NOT _066_ (
    .A(dataout1[2]),
    .Y(_020_)
  );
  NOR _067_ (
    .A(_020_),
    .B(_005_),
    .Y(_021_)
  );
  NAND _068_ (
    .A(_021_),
    .B(_011_),
    .Y(_022_)
  );
  NAND _069_ (
    .A(_004_),
    .B(data_in[2]),
    .Y(_023_)
  );
  NAND _070_ (
    .A(_023_),
    .B(_022_),
    .Y(_001_[2])
  );
  NOT _071_ (
    .A(dataout1[3]),
    .Y(_024_)
  );
  NOR _072_ (
    .A(_024_),
    .B(_005_),
    .Y(_025_)
  );
  NAND _073_ (
    .A(_025_),
    .B(_011_),
    .Y(_026_)
  );
  NAND _074_ (
    .A(_004_),
    .B(data_in[3]),
    .Y(_027_)
  );
  NAND _075_ (
    .A(_027_),
    .B(_026_),
    .Y(_001_[3])
  );
  NOR _076_ (
    .A(_006_),
    .B(_009_),
    .Y(_028_)
  );
  NOR _077_ (
    .A(valid_0),
    .B(valid_in),
    .Y(_029_)
  );
  NOR _078_ (
    .A(_029_),
    .B(_028_),
    .Y(_030_)
  );
  NOT _079_ (
    .A(dataout0[0]),
    .Y(_031_)
  );
  NOR _080_ (
    .A(_031_),
    .B(_005_),
    .Y(_032_)
  );
  NAND _081_ (
    .A(_032_),
    .B(_030_),
    .Y(_033_)
  );
  NAND _082_ (
    .A(_003_),
    .B(data_in[0]),
    .Y(_034_)
  );
  NAND _083_ (
    .A(_034_),
    .B(_033_),
    .Y(_000_[0])
  );
  NOT _084_ (
    .A(dataout0[1]),
    .Y(_035_)
  );
  NOR _085_ (
    .A(_035_),
    .B(_005_),
    .Y(_036_)
  );
  NAND _086_ (
    .A(_036_),
    .B(_030_),
    .Y(_037_)
  );
  NAND _087_ (
    .A(_003_),
    .B(data_in[1]),
    .Y(_038_)
  );
  NAND _088_ (
    .A(_038_),
    .B(_037_),
    .Y(_000_[1])
  );
  NOT _089_ (
    .A(dataout0[2]),
    .Y(_039_)
  );
  NOR _090_ (
    .A(_039_),
    .B(_005_),
    .Y(_040_)
  );
  NAND _091_ (
    .A(_040_),
    .B(_030_),
    .Y(_041_)
  );
  NAND _092_ (
    .A(_003_),
    .B(data_in[2]),
    .Y(_042_)
  );
  NAND _093_ (
    .A(_042_),
    .B(_041_),
    .Y(_000_[2])
  );
  NOT _094_ (
    .A(dataout0[3]),
    .Y(_043_)
  );
  NOR _095_ (
    .A(_043_),
    .B(_005_),
    .Y(_044_)
  );
  NAND _096_ (
    .A(_044_),
    .B(_030_),
    .Y(_045_)
  );
  NAND _097_ (
    .A(_003_),
    .B(data_in[3]),
    .Y(_046_)
  );
  NAND _098_ (
    .A(_046_),
    .B(_045_),
    .Y(_000_[3])
  );
  NOR _099_ (
    .A(selectorL1),
    .B(_005_),
    .Y(_002_)
  );
  DFF _100_ (
    .C(clk),
    .D(_000_[0]),
    .Q(dataout0[0])
  );
  DFF _101_ (
    .C(clk),
    .D(_000_[1]),
    .Q(dataout0[1])
  );
  DFF _102_ (
    .C(clk),
    .D(_000_[2]),
    .Q(dataout0[2])
  );
  DFF _103_ (
    .C(clk),
    .D(_000_[3]),
    .Q(dataout0[3])
  );
  DFF _104_ (
    .C(clk),
    .D(_001_[0]),
    .Q(dataout1[0])
  );
  DFF _105_ (
    .C(clk),
    .D(_001_[1]),
    .Q(dataout1[1])
  );
  DFF _106_ (
    .C(clk),
    .D(_001_[2]),
    .Q(dataout1[2])
  );
  DFF _107_ (
    .C(clk),
    .D(_001_[3]),
    .Q(dataout1[3])
  );
  DFF _108_ (
    .C(clk),
    .D(_003_),
    .Q(valid_0)
  );
  DFF _109_ (
    .C(clk),
    .D(_004_),
    .Q(valid_1)
  );
  DFF _110_ (
    .C(clk),
    .D(_002_),
    .Q(selectorL1)
  );
endmodule

Demux/demux.v
//IE-0523 Circuitos Digitales II
//Proyecto2. demux.
//Elaborado por: César Valverde Zuñiga	A86605		
//I Ciclo 2019

// Este módulo genera las salidas dataout0 y dataout1, recibiendo como entrada datain a una frecuencia de f.

//`timescale 1ns/100ps

module demux(		input clk,
				input reset_L,
				input valid_in,
				input [3:0] data_in,
				output reg [3:0] dataout0,
				output reg [3:0] dataout1,
				output reg valid_0,
            			output reg valid_1
);

        //Registros Internos
	reg selectorL1;

	always @(posedge clk) begin
		selectorL1 <= ~selectorL1;
		if((!reset_L))begin
		dataout1<= 0;
		dataout0 <= 0;
		valid_0 <= 0;
           	valid_1 <= 0;
           	selectorL1 <= 0;
		end
		else if (~valid_in)begin
				if (valid_0==0)begin
				dataout0 <= 0;
				end
				else begin
				valid_0 <= 0;
				end 
				if (valid_1==0)begin
				dataout1 <= 0;
				end
				else if (valid_1==1)begin
				valid_1 <= 0;
				end 
			end
		else if(valid_in)begin 
				if(~selectorL1)begin
					dataout1 <= data_in;
					valid_1 <=1;
					valid_0 <=0;

				end
				else begin
					dataout0 <= data_in;
					valid_0 <= 1;
					valid_1 <=0;
				end
		end
	  end
	
endmodule

Demux/demux_BancoDePruebas.v
//IE-0523 Circuitos Digitales II
//Proyecto2. Módulo Test_bench del Demux.
//Elaborado por el estudiante: César Valverde Zuñiga	A86605		
//I Ciclo 2019

`timescale 1ns / 100ps
`include "demux.v"
`include "probador.v"
`include "demuxEstructural.v"
`include "cmos_cells.v"

module Test_Bench;

	wire reset_L, clk, valid_in, valid_0, valid_1;
	wire [3:0] dataout0, dataout1, data_in;
	
	//Instancia del módulo Demux Conductual
	demux DM(
				.clk 	(clk),
				.reset_L(reset_L),
				.valid_in(valid_in),
				.valid_0(valid_0),
				.valid_1(valid_1),
				.data_in (data_in),
				.dataout0 (dataout0),
				.dataout1 (dataout1)
	);

	//Instancia del módulo Demux Estrutural
	demuxEstructural DMEstr(
				.clk 	(clk),
				.reset_L(reset_L),
				.valid_in(valid_in),
				.valid_0(valid_0),
				.valid_1(valid_1),
				.data_in (data_in),
				.dataout0 (dataout0),
				.dataout1 (dataout1)
	);
	
	//Instancia del Probador Demux
	probador PDMux(	.clk (clk),
				.valid_0(valid_0),
				.valid_1(valid_1),
					.reset_L (reset_L),
					.valid_in(valid_in), 
					.dataout0 (dataout0),
					.dataout1 (dataout1),
					.data_in (data_in)
	);


endmodule

Memoria/cmos_cells.v

module BUF(A, Y);
input A;
output Y;
assign Y = A;
endmodule

module NOT(A, Y);
input A;
output Y;
assign Y = ~A;
endmodule

module NAND(A, B, Y);
input A, B;
output Y;
assign Y = ~(A & B);
endmodule

module NOR(A, B, Y);
input A, B;
output Y;
assign Y = ~(A | B);
endmodule

module DFF(C, D, Q);
input C, D;
output reg Q;
always @(posedge C)
	Q <= D;
endmodule

module DFFSR(C, D, Q, S, R);
input C, D, S, R;
output reg Q;
always @(posedge C, posedge S, posedge R)
	if (S)
		Q <= 1'b1;
	else if (R)
		Q <= 1'b0;
	else
		Q <= D;
endmodule

Demux/demux.vcd
$date
	Thu Jul  4 18:35:29 2019
$end
$version
	Icarus Verilog
$end
$timescale
	100ps
$end
$scope module BUF $end
$var wire 1 ! A $end
$var wire 1 " Y $end
$upscope $end
$scope module DFFSR $end
$var wire 1 # C $end
$var wire 1 $ D $end
$var wire 1 % R $end
$var wire 1 & S $end
$var reg 1 ' Q $end
$upscope $end
$scope module Test_Bench $end
$var wire 4 ( dataout0 [3:0] $end
$var wire 4 ) dataout1 [3:0] $end
$var wire 1 * valid_0 $end
$var wire 1 + valid_1 $end
$var wire 1 , valid_in $end
$var wire 1 - reset_L $end
$var wire 4 . data_in [3:0] $end
$var wire 1 / clk $end
$scope module DM $end
$var wire 1 , valid_in $end
$var wire 1 - reset_L $end
$var wire 4 0 data_in [3:0] $end
$var wire 1 / clk $end
$var reg 4 1 dataout0 [3:0] $end
$var reg 4 2 dataout1 [3:0] $end
$var reg 1 3 selectorL1 $end
$var reg 1 4 valid_0 $end
$var reg 1 5 valid_1 $end
$upscope $end
$scope module DMEstr $end
$var wire 4 6 dataout0 [3:0] $end
$var wire 4 7 dataout1 [3:0] $end
$var wire 1 * valid_0 $end
$var wire 1 + valid_1 $end
$var wire 1 , valid_in $end
$var wire 1 8 selectorL1 $end
$var wire 1 - reset_L $end
$var wire 4 9 data_in [3:0] $end
$var wire 1 / clk $end
$var wire 1 : _046_ $end
$var wire 1 ; _045_ $end
$var wire 1 < _044_ $end
$var wire 1 = _043_ $end
$var wire 1 > _042_ $end
$var wire 1 ? _041_ $end
$var wire 1 @ _040_ $end
$var wire 1 A _039_ $end
$var wire 1 B _038_ $end
$var wire 1 C _037_ $end
$var wire 1 D _036_ $end
$var wire 1 E _035_ $end
$var wire 1 F _034_ $end
$var wire 1 G _033_ $end
$var wire 1 H _032_ $end
$var wire 1 I _031_ $end
$var wire 1 J _030_ $end
$var wire 1 K _029_ $end
$var wire 1 L _028_ $end
$var wire 1 M _027_ $end
$var wire 1 N _026_ $end
$var wire 1 O _025_ $end
$var wire 1 P _024_ $end
$var wire 1 Q _023_ $end
$var wire 1 R _022_ $end
$var wire 1 S _021_ $end
$var wire 1 T _020_ $end
$var wire 1 U _019_ $end
$var wire 1 V _018_ $end
$var wire 1 W _017_ $end
$var wire 1 X _016_ $end
$var wire 1 Y _015_ $end
$var wire 1 Z _014_ $end
$var wire 1 [ _013_ $end
$var wire 1 \ _012_ $end
$var wire 1 ] _011_ $end
$var wire 1 ^ _010_ $end
$var wire 1 _ _009_ $end
$var wire 1 ` _008_ $end
$var wire 1 a _007_ $end
$var wire 1 b _006_ $end
$var wire 1 c _005_ $end
$var wire 1 d _004_ $end
$var wire 1 e _003_ $end
$var wire 1 f _002_ $end
$var wire 4 g _001_ [3:0] $end
$var wire 4 h _000_ [3:0] $end
$scope module _047_ $end
$var wire 1 c Y $end
$var wire 1 - A $end
$upscope $end
$scope module _048_ $end
$var wire 1 b Y $end
$var wire 1 8 A $end
$upscope $end
$scope module _049_ $end
$var wire 1 b A $end
$var wire 1 a Y $end
$var wire 1 , B $end
$upscope $end
$scope module _050_ $end
$var wire 1 a A $end
$var wire 1 c B $end
$var wire 1 d Y $end
$upscope $end
$scope module _051_ $end
$var wire 1 ` Y $end
$var wire 1 , B $end
$var wire 1 8 A $end
$upscope $end
$scope module _052_ $end
$var wire 1 ` A $end
$var wire 1 c B $end
$var wire 1 e Y $end
$upscope $end
$scope module _053_ $end
$var wire 1 _ Y $end
$var wire 1 , A $end
$upscope $end
$scope module _054_ $end
$var wire 1 + A $end
$var wire 1 _ B $end
$var wire 1 ^ Y $end
$upscope $end
$scope module _055_ $end
$var wire 1 ^ A $end
$var wire 1 ` B $end
$var wire 1 ] Y $end
$upscope $end
$scope module _056_ $end
$var wire 1 i A $end
$var wire 1 \ Y $end
$upscope $end
$scope module _057_ $end
$var wire 1 \ A $end
$var wire 1 c B $end
$var wire 1 [ Y $end
$upscope $end
$scope module _058_ $end
$var wire 1 [ A $end
$var wire 1 ] B $end
$var wire 1 Z Y $end
$upscope $end
$scope module _059_ $end
$var wire 1 d A $end
$var wire 1 j B $end
$var wire 1 Y Y $end
$upscope $end
$scope module _060_ $end
$var wire 1 Y A $end
$var wire 1 Z B $end
$var wire 1 k Y $end
$upscope $end
$scope module _061_ $end
$var wire 1 l A $end
$var wire 1 X Y $end
$upscope $end
$scope module _062_ $end
$var wire 1 X A $end
$var wire 1 c B $end
$var wire 1 W Y $end
$upscope $end
$scope module _063_ $end
$var wire 1 W A $end
$var wire 1 ] B $end
$var wire 1 V Y $end
$upscope $end
$scope module _064_ $end
$var wire 1 d A $end
$var wire 1 m B $end
$var wire 1 U Y $end
$upscope $end
$scope module _065_ $end
$var wire 1 U A $end
$var wire 1 V B $end
$var wire 1 n Y $end
$upscope $end
$scope module _066_ $end
$var wire 1 o A $end
$var wire 1 T Y $end
$upscope $end
$scope module _067_ $end
$var wire 1 T A $end
$var wire 1 c B $end
$var wire 1 S Y $end
$upscope $end
$scope module _068_ $end
$var wire 1 S A $end
$var wire 1 ] B $end
$var wire 1 R Y $end
$upscope $end
$scope module _069_ $end
$var wire 1 d A $end
$var wire 1 p B $end
$var wire 1 Q Y $end
$upscope $end
$scope module _070_ $end
$var wire 1 Q A $end
$var wire 1 R B $end
$var wire 1 q Y $end
$upscope $end
$scope module _071_ $end
$var wire 1 r A $end
$var wire 1 P Y $end
$upscope $end
$scope module _072_ $end
$var wire 1 P A $end
$var wire 1 c B $end
$var wire 1 O Y $end
$upscope $end
$scope module _073_ $end
$var wire 1 O A $end
$var wire 1 ] B $end
$var wire 1 N Y $end
$upscope $end
$scope module _074_ $end
$var wire 1 d A $end
$var wire 1 s B $end
$var wire 1 M Y $end
$upscope $end
$scope module _075_ $end
$var wire 1 M A $end
$var wire 1 N B $end
$var wire 1 t Y $end
$upscope $end
$scope module _076_ $end
$var wire 1 b A $end
$var wire 1 _ B $end
$var wire 1 L Y $end
$upscope $end
$scope module _077_ $end
$var wire 1 * A $end
$var wire 1 K Y $end
$var wire 1 , B $end
$upscope $end
$scope module _078_ $end
$var wire 1 K A $end
$var wire 1 L B $end
$var wire 1 J Y $end
$upscope $end
$scope module _079_ $end
$var wire 1 u A $end
$var wire 1 I Y $end
$upscope $end
$scope module _080_ $end
$var wire 1 I A $end
$var wire 1 c B $end
$var wire 1 H Y $end
$upscope $end
$scope module _081_ $end
$var wire 1 H A $end
$var wire 1 J B $end
$var wire 1 G Y $end
$upscope $end
$scope module _082_ $end
$var wire 1 e A $end
$var wire 1 v B $end
$var wire 1 F Y $end
$upscope $end
$scope module _083_ $end
$var wire 1 F A $end
$var wire 1 G B $end
$var wire 1 w Y $end
$upscope $end
$scope module _084_ $end
$var wire 1 x A $end
$var wire 1 E Y $end
$upscope $end
$scope module _085_ $end
$var wire 1 E A $end
$var wire 1 c B $end
$var wire 1 D Y $end
$upscope $end
$scope module _086_ $end
$var wire 1 D A $end
$var wire 1 J B $end
$var wire 1 C Y $end
$upscope $end
$scope module _087_ $end
$var wire 1 e A $end
$var wire 1 y B $end
$var wire 1 B Y $end
$upscope $end
$scope module _088_ $end
$var wire 1 B A $end
$var wire 1 C B $end
$var wire 1 z Y $end
$upscope $end
$scope module _089_ $end
$var wire 1 { A $end
$var wire 1 A Y $end
$upscope $end
$scope module _090_ $end
$var wire 1 A A $end
$var wire 1 c B $end
$var wire 1 @ Y $end
$upscope $end
$scope module _091_ $end
$var wire 1 @ A $end
$var wire 1 J B $end
$var wire 1 ? Y $end
$upscope $end
$scope module _092_ $end
$var wire 1 e A $end
$var wire 1 | B $end
$var wire 1 > Y $end
$upscope $end
$scope module _093_ $end
$var wire 1 > A $end
$var wire 1 ? B $end
$var wire 1 } Y $end
$upscope $end
$scope module _094_ $end
$var wire 1 ~ A $end
$var wire 1 = Y $end
$upscope $end
$scope module _095_ $end
$var wire 1 = A $end
$var wire 1 c B $end
$var wire 1 < Y $end
$upscope $end
$scope module _096_ $end
$var wire 1 < A $end
$var wire 1 J B $end
$var wire 1 ; Y $end
$upscope $end
$scope module _097_ $end
$var wire 1 e A $end
$var wire 1 !" B $end
$var wire 1 : Y $end
$upscope $end
$scope module _098_ $end
$var wire 1 : A $end
$var wire 1 ; B $end
$var wire 1 "" Y $end
$upscope $end
$scope module _099_ $end
$var wire 1 c B $end
$var wire 1 f Y $end
$var wire 1 8 A $end
$upscope $end
$scope module _100_ $end
$var wire 1 #" D $end
$var wire 1 / C $end
$var reg 1 $" Q $end
$upscope $end
$scope module _101_ $end
$var wire 1 %" D $end
$var wire 1 / C $end
$var reg 1 &" Q $end
$upscope $end
$scope module _102_ $end
$var wire 1 '" D $end
$var wire 1 / C $end
$var reg 1 (" Q $end
$upscope $end
$scope module _103_ $end
$var wire 1 )" D $end
$var wire 1 / C $end
$var reg 1 *" Q $end
$upscope $end
$scope module _104_ $end
$var wire 1 +" D $end
$var wire 1 / C $end
$var reg 1 ," Q $end
$upscope $end
$scope module _105_ $end
$var wire 1 -" D $end
$var wire 1 / C $end
$var reg 1 ." Q $end
$upscope $end
$scope module _106_ $end
$var wire 1 /" D $end
$var wire 1 / C $end
$var reg 1 0" Q $end
$upscope $end
$scope module _107_ $end
$var wire 1 1" D $end
$var wire 1 / C $end
$var reg 1 2" Q $end
$upscope $end
$scope module _108_ $end
$var wire 1 e D $end
$var wire 1 / C $end
$var reg 1 3" Q $end
$upscope $end
$scope module _109_ $end
$var wire 1 d D $end
$var wire 1 / C $end
$var reg 1 4" Q $end
$upscope $end
$scope module _110_ $end
$var wire 1 f D $end
$var wire 1 / C $end
$var reg 1 8 Q $end
$upscope $end
$upscope $end
$scope module PDMux $end
$var wire 4 5" dataout0 [3:0] $end
$var wire 4 6" dataout1 [3:0] $end
$var wire 1 * valid_0 $end
$var wire 1 + valid_1 $end
$var reg 1 / clk $end
$var reg 4 7" data_in [3:0] $end
$var reg 1 - reset_L $end
$var reg 1 , valid_in $end
$upscope $end
$upscope $end
$enddefinitions $end
#0
$dumpvars
bx 7"
bx 6"
bx 5"
x4"
x3"
x2"
01"
x0"
0/"
x."
0-"
x,"
0+"
x*"
0)"
x("
0'"
x&"
0%"
x$"
0#"
0""
x!"
x~
0}
x|
x{
0z
xy
xx
0w
xv
xu
0t
xs
xr
0q
xp
xo
0n
xm
xl
0k
xj
xi
b0 h
b0 g
0f
0e
0d
1c
xb
xa
x`
x_
x^
x]
x\
0[
1Z
1Y
xX
0W
1V
1U
xT
0S
1R
1Q
xP
0O
1N
1M
xL
xK
xJ
xI
0H
1G
1F
xE
0D
1C
1B
xA
0@
1?
1>
x=
0<
1;
1:
bx 9
x8
bx 7
bx 6
x5
x4
x3
bx 2
bx 1
bx 0
0/
bx .
0-
x,
x+
x*
bx )
bx (
x'
z&
z%
z$
z#
z"
z!
$end
#20
0J
0]
0[
0W
0S
0O
0H
0D
0@
0<
0L
1^
1I
1E
1A
1=
1\
1X
1T
1P
1f
1K
1`
1a
0u
0x
0{
0~
0i
0l
0o
0r
1b
0c
1_
0!"
0|
0y
0v
0s
0p
0m
0j
03
0+
05
0*
04
b0 (
b0 6
b0 5"
b0 1
b0 )
b0 7
b0 6"
b0 2
0$"
0&"
0("
0*"
0,"
0."
00"
02"
03"
04"
08
1-
0,
b0 .
b0 0
b0 9
b0 7"
1/
#40
0/
#60
1%"
1)"
1z
b1010 h
1""
0B
0:
1e
1]
1L
0K
0f
0`
0_
1!"
1y
1s
1m
0b
1,
b1010 .
b1010 0
b1010 9
b1010 7"
18
13
1/
#80
0/
#100
1+"
1-"
1/"
11"
1k
1n
1q
b1111 g
1t
0Y
0U
0Q
0M
0C
0;
1B
1:
0'"
0#"
1d
1J
0}
b1010 h
0w
1D
1<
0e
0]
0a
0L
1>
1F
0E
0=
1f
1`
1x
1~
1b
1|
1v
1p
1j
14
b1010 1
03
1&"
b1010 (
b1010 6
b1010 5"
1*"
1*
13"
08
b1111 .
b1111 0
b1111 9
b1111 7"
1/
#120
0/
#140
1-"
1/"
11"
0%"
0)"
1n
1q
1t
0z
b0 h
0""
0Z
0V
0R
0N
1U
1Q
1M
1+"
1C
1;
1]
b1111 g
1k
0d
0J
1[
1W
1S
1O
0^
1Y
1a
0f
1K
0\
0X
0T
0P
1_
0v
0j
0b
1i
1l
1o
1r
0,
b1110 .
b1110 0
b1110 9
b1110 7"
18
14"
03"
12"
10"
1."
1,"
0*
04
1+
15
b1111 )
b1111 7
b1111 6"
b1111 2
13
1/
#160
0/
#180
0+"
0-"
0/"
01"
0k
0n
0q
b0 g
0t
1Z
1V
1R
1N
0D
0<
0]
1E
1=
1^
1f
0x
0~
1b
0y
1v
0m
1j
05
b0 1
03
0&"
b0 (
b0 6
b0 5"
0*"
0+
04"
08
b1101 .
b1101 0
b1101 9
b1101 7"
1/
#200
0/
#220
1%"
b10 h
1z
0B
1e
1]
0[
0W
0S
0O
1L
0K
0f
0`
1\
1X
1T
1P
0_
0!"
0|
1y
0v
0s
0p
1m
0j
0b
0i
0l
0o
0r
1,
b10 .
b10 0
b10 9
b10 7"
18
02"
00"
0."
0,"
b0 )
b0 7
b0 6"
b0 2
13
1/
#240
0/
#260
1+"
1-"
11"
1k
1n
b1011 g
1t
0Y
0U
0M
0C
1B
0)"
0#"
1d
1J
0""
b10 h
0w
1D
0e
0]
0a
0L
1:
1F
0E
1f
1`
1x
1b
1!"
1v
1s
1j
14
b10 1
03
b10 (
b10 6
b10 5"
1&"
1*
13"
08
b1011 .
b1011 0
b1011 9
b1011 7"
1/
#280
0/
#300
1#"
b11 h
1w
1Y
1U
1C
11"
0F
0B
0Z
0V
0N
b1011 g
1t
0d
0J
1e
1]
1[
1W
1O
1M
1a
1L
0f
0`
0\
0X
0P
0!"
0s
0b
1i
1l
1r
b11 .
b11 0
b11 9
b11 7"
18
14"
03"
12"
1."
1,"
0*
04
1+
15
b1011 )
b1011 7
b1011 6"
b1011 2
13
1/
#320
0/
#340
1/"
0+"
0-"
01"
1q
0k
0n
b100 g
0t
0Q
0C
0G
1Z
1V
1N
0'"
1%"
1#"
1d
1J
0}
1z
b11 h
1w
1H
0e
0]
0a
0L
1>
1B
1F
0I
1f
1`
1u
1b
1|
0y
0v
1p
0m
0j
05
14
b11 1
03
b11 (
b11 6
b11 5"
1$"
1*
13"
0+
04"
08
b100 .
b100 0
b100 9
b100 7"
1/
#360
0/
#380
1/"
0#"
0%"
1q
0w
b0 h
0z
0R
1Q
0+"
1G
1C
1]
b100 g
0k
0d
0J
0[
0W
1S
0O
0^
1Y
1a
0f
1K
1\
1X
0T
1P
1_
1v
1j
0b
0i
0l
1o
0r
0,
b101 .
b101 0
b101 9
b101 7"
18
14"
03"
02"
10"
0."
0,"
0*
04
1+
15
b100 )
b100 7
b100 6"
b100 2
13
1/
#400
0/
#420
0/"
b0 g
0q
1R
0H
0D
0]
1I
1E
1^
1f
0u
0x
1b
05
b0 1
03
0$"
b0 (
b0 6
b0 5"
0&"
0+
04"
08
1/
#440
0/
#460
0S
0f
1T
0b
0o
18
00"
b0 )
b0 7
b0 6"
b0 2
13
1/
#480
0/
#500
1f
1b
03
08
1/
#520
0/
#540
0f
0b
18
13
1/
#560
0/
#580
1f
1b
03
08
1/
#600
0/
#620
0f
0b
18
13
1/
#640
0/
#660
1f
1b
03
08
1/
