Demux/Demux_D0_D1/probador.v
module probador(		    		input valid_0,
						input valid_1,
						input wire [5:0] dataout0,
						input wire [5:0] dataout1,
						output reg reset_L,
						output reg clk,
						output reg valid_in,
						output reg [5:0] data_in
						);

initial clk <=0;
always begin
	#2 clk <= ~clk;
end

initial begin
	$dumpfile("Demux_D0_D1.vcd");
	$dumpvars;

	reset_L <= 1'b0;
	@(posedge clk)
	data_in<=6'h34;
	valid_in<=0;
	reset_L <= 1'b1;

	@(posedge clk)
	data_in <= 6'h32;
	valid_in<=1;

	@(posedge clk)
	data_in <= 6'h37;
	valid_in<=1;

	@(posedge clk)
	data_in <= 6'h7E;
	valid_in<=0;

	@(posedge clk)
	data_in <= 6'h2D;
	valid_in<=0;

	@(posedge clk)
	data_in <= 6'h12;
	valid_in<=1;

	@(posedge clk)
	data_in <= 6'h13;
	valid_in<=1;

	@(posedge clk)
	reset_L <= 1'b0;

	@(posedge clk)
	reset_L <= 1'b1;

	@(posedge clk)
	data_in <= 6'h23;
	valid_in<=1;

	@(posedge clk)
	data_in <= 6'h4;
	valid_in<=1;

	@(posedge clk)
	data_in <= 6'h25;
	valid_in<=0;

	#30 $finish;
end

endmodule

LogicaMasterPrueba2/Demux_D0_D1.v
module Demux_D0_D1(
							input clk,
							input reset_L,
							input valid_in,
							input [5:0] data_in,
							output reg [5:0] dataout0,
							output reg [5:0] dataout1,
							output reg valid_0,
        			output reg valid_1
);

        //Registros Internos
	reg selectorL1;

always @(*) begin
	if((!reset_L))begin
	selectorL1 <=0;
	end
	else begin
	selectorL1 <=data_in [4];
	end
end

	always @(posedge clk) begin
		if((!reset_L))begin
		dataout1<= 0;
		dataout0 <= 0;
		valid_0 <= 0;
    valid_1 <= 0;

		end
		else if (~valid_in)begin
				if (valid_0==0)begin
				dataout0 <= 0;
				end
				else begin
				valid_0 <= 0;
				end
				if (valid_1==0)begin
				dataout1 <= 0;
				end
				else if (valid_1==1)begin
				valid_1 <= 0;
				end
			end
		else if(valid_in)begin
				if(selectorL1)begin
					dataout1 <= data_in;
					valid_1 <=1;
					valid_0 <=0;

				end
				else begin
					dataout0 <= data_in;
					valid_0 <= 1;
					valid_1 <=0;
				end
		end
	  end

endmodule

Demux/Demux_D0_D1/Demux_D0_D1_BancoDePruebas.v
//IE-0523 Circuitos Digitales II
//Proyecto2. Módulo Test_bench del Demux.
//Elaborado por el estudiante: César Valverde Zuñiga	A86605
//I Ciclo 2019

`timescale 1ns / 100ps
`include "Demux_D0_D1.v"
`include "probador.v"
`include "Demux_D0_D1_Estructural.v"
`include "cmos_cells.v"

module Test_Bench;

	wire reset_L, clk, valid_in, valid_0, valid_1;
	wire [5:0] dataout0, dataout1, data_in;

	//Instancia del módulo Demux Conductual
	Demux_D0_D1 DM(
				.clk 	(clk),
				.reset_L(reset_L),
				.valid_in(valid_in),
				.valid_0(valid_0),
				.valid_1(valid_1),
				.data_in (data_in),
				.dataout0 (dataout0),
				.dataout1 (dataout1)
	);

	//Instancia del módulo Demux Estrutural
	Demux_D0_D1 DMEstr(
				.clk 	(clk),
				.reset_L(reset_L),
				.valid_in(valid_in),
				.valid_0(valid_0),
				.valid_1(valid_1),
				.data_in (data_in),
				.dataout0 (dataout0),
				.dataout1 (dataout1)
	);

	//Instancia del Probador Demux
	probador PDMux(	.clk (clk),
				.valid_0(valid_0),
				.valid_1(valid_1),
					.reset_L (reset_L),
					.valid_in(valid_in),
					.dataout0 (dataout0),
					.dataout1 (dataout1),
					.data_in (data_in)
	);


endmodule

Demux/Demux_D0_D1/Demux_D0_D1_Estructural.v
/* Generated by Yosys 0.7 (git sha1 61f6811, gcc 6.2.0-11ubuntu1 -O2 -fdebug-prefix-map=/build/yosys-OIL3SR/yosys-0.7=. -fstack-protector-strong -fPIC -Os) */

module Demux_D0_D1_Estructural(clk, reset_L, valid_in, data_in, dataout0, dataout1, valid_0, valid_1);
  wire [5:0] _000_;
  wire [5:0] _001_;
  wire _002_;
  wire _003_;
  wire _004_;
  wire _005_;
  wire _006_;
  wire _007_;
  wire _008_;
  wire _009_;
  wire _010_;
  wire _011_;
  wire _012_;
  wire _013_;
  wire _014_;
  wire _015_;
  wire _016_;
  wire _017_;
  wire _018_;
  wire _019_;
  wire _020_;
  wire _021_;
  wire _022_;
  wire _023_;
  wire _024_;
  wire _025_;
  wire _026_;
  wire _027_;
  wire _028_;
  wire _029_;
  wire _030_;
  wire _031_;
  wire _032_;
  wire _033_;
  wire _034_;
  wire _035_;
  wire _036_;
  wire _037_;
  wire _038_;
  wire _039_;
  wire _040_;
  wire _041_;
  wire _042_;
  wire _043_;
  wire _044_;
  wire _045_;
  wire _046_;
  wire _047_;
  wire _048_;
  wire _049_;
  wire _050_;
  wire _051_;
  wire _052_;
  wire _053_;
  input clk;
  input [5:0] data_in;
  output [5:0] dataout0;
  output [5:0] dataout1;
  input reset_L;
  output valid_0;
  output valid_1;
  input valid_in;
  NOT _054_ (
    .A(data_in[4]),
    .Y(_004_)
  );
  NAND _055_ (
    .A(valid_in),
    .B(reset_L),
    .Y(_005_)
  );
  NOR _056_ (
    .A(_005_),
    .B(_004_),
    .Y(_003_)
  );
  NOR _057_ (
    .A(_005_),
    .B(data_in[4]),
    .Y(_002_)
  );
  NOR _058_ (
    .A(valid_1),
    .B(valid_in),
    .Y(_006_)
  );
  NOR _059_ (
    .A(_006_),
    .B(_003_),
    .Y(_007_)
  );
  NOT _060_ (
    .A(reset_L),
    .Y(_008_)
  );
  NOT _061_ (
    .A(dataout1[0]),
    .Y(_009_)
  );
  NOR _062_ (
    .A(_009_),
    .B(_008_),
    .Y(_010_)
  );
  NAND _063_ (
    .A(_010_),
    .B(_007_),
    .Y(_011_)
  );
  NAND _064_ (
    .A(_003_),
    .B(data_in[0]),
    .Y(_012_)
  );
  NAND _065_ (
    .A(_012_),
    .B(_011_),
    .Y(_001_[0])
  );
  NOT _066_ (
    .A(dataout1[1]),
    .Y(_013_)
  );
  NOR _067_ (
    .A(_013_),
    .B(_008_),
    .Y(_014_)
  );
  NAND _068_ (
    .A(_014_),
    .B(_007_),
    .Y(_015_)
  );
  NAND _069_ (
    .A(_003_),
    .B(data_in[1]),
    .Y(_016_)
  );
  NAND _070_ (
    .A(_016_),
    .B(_015_),
    .Y(_001_[1])
  );
  NOT _071_ (
    .A(dataout1[2]),
    .Y(_017_)
  );
  NOR _072_ (
    .A(_017_),
    .B(_008_),
    .Y(_018_)
  );
  NAND _073_ (
    .A(_018_),
    .B(_007_),
    .Y(_019_)
  );
  NAND _074_ (
    .A(_003_),
    .B(data_in[2]),
    .Y(_020_)
  );
  NAND _075_ (
    .A(_020_),
    .B(_019_),
    .Y(_001_[2])
  );
  NOT _076_ (
    .A(dataout1[3]),
    .Y(_021_)
  );
  NOR _077_ (
    .A(_021_),
    .B(_008_),
    .Y(_022_)
  );
  NAND _078_ (
    .A(_022_),
    .B(_007_),
    .Y(_023_)
  );
  NAND _079_ (
    .A(_003_),
    .B(data_in[3]),
    .Y(_024_)
  );
  NAND _080_ (
    .A(_024_),
    .B(_023_),
    .Y(_001_[3])
  );
  NOT _081_ (
    .A(valid_in),
    .Y(_025_)
  );
  NOR _082_ (
    .A(_025_),
    .B(_008_),
    .Y(_026_)
  );
  NAND _083_ (
    .A(_026_),
    .B(data_in[4]),
    .Y(_027_)
  );
  NOT _084_ (
    .A(_006_),
    .Y(_028_)
  );
  NOT _085_ (
    .A(dataout1[4]),
    .Y(_029_)
  );
  NOR _086_ (
    .A(_029_),
    .B(_008_),
    .Y(_030_)
  );
  NAND _087_ (
    .A(_030_),
    .B(_028_),
    .Y(_031_)
  );
  NAND _088_ (
    .A(_031_),
    .B(_027_),
    .Y(_001_[4])
  );
  NOT _089_ (
    .A(dataout1[5]),
    .Y(_032_)
  );
  NOR _090_ (
    .A(_032_),
    .B(_008_),
    .Y(_033_)
  );
  NAND _091_ (
    .A(_033_),
    .B(_007_),
    .Y(_034_)
  );
  NAND _092_ (
    .A(_003_),
    .B(data_in[5]),
    .Y(_035_)
  );
  NAND _093_ (
    .A(_035_),
    .B(_034_),
    .Y(_001_[5])
  );
  NAND _094_ (
    .A(_002_),
    .B(data_in[0]),
    .Y(_036_)
  );
  NOR _095_ (
    .A(valid_in),
    .B(_008_),
    .Y(_037_)
  );
  NAND _096_ (
    .A(_037_),
    .B(valid_0),
    .Y(_038_)
  );
  NAND _097_ (
    .A(_038_),
    .B(_027_),
    .Y(_039_)
  );
  NAND _098_ (
    .A(_039_),
    .B(dataout0[0]),
    .Y(_040_)
  );
  NAND _099_ (
    .A(_040_),
    .B(_036_),
    .Y(_000_[0])
  );
  NAND _100_ (
    .A(_002_),
    .B(data_in[1]),
    .Y(_041_)
  );
  NAND _101_ (
    .A(_039_),
    .B(dataout0[1]),
    .Y(_042_)
  );
  NAND _102_ (
    .A(_042_),
    .B(_041_),
    .Y(_000_[1])
  );
  NAND _103_ (
    .A(_002_),
    .B(data_in[2]),
    .Y(_043_)
  );
  NAND _104_ (
    .A(_039_),
    .B(dataout0[2]),
    .Y(_044_)
  );
  NAND _105_ (
    .A(_044_),
    .B(_043_),
    .Y(_000_[2])
  );
  NAND _106_ (
    .A(_002_),
    .B(data_in[3]),
    .Y(_045_)
  );
  NAND _107_ (
    .A(_039_),
    .B(dataout0[3]),
    .Y(_046_)
  );
  NAND _108_ (
    .A(_046_),
    .B(_045_),
    .Y(_000_[3])
  );
  NOT _109_ (
    .A(dataout0[4]),
    .Y(_047_)
  );
  NOT _110_ (
    .A(valid_0),
    .Y(_048_)
  );
  NAND _111_ (
    .A(_025_),
    .B(reset_L),
    .Y(_049_)
  );
  NOR _112_ (
    .A(_049_),
    .B(_048_),
    .Y(_050_)
  );
  NOR _113_ (
    .A(_050_),
    .B(_003_),
    .Y(_051_)
  );
  NOR _114_ (
    .A(_051_),
    .B(_047_),
    .Y(_000_[4])
  );
  NAND _115_ (
    .A(_002_),
    .B(data_in[5]),
    .Y(_052_)
  );
  NAND _116_ (
    .A(_039_),
    .B(dataout0[5]),
    .Y(_053_)
  );
  NAND _117_ (
    .A(_053_),
    .B(_052_),
    .Y(_000_[5])
  );
  DFF _118_ (
    .C(clk),
    .D(_000_[0]),
    .Q(dataout0[0])
  );
  DFF _119_ (
    .C(clk),
    .D(_000_[1]),
    .Q(dataout0[1])
  );
  DFF _120_ (
    .C(clk),
    .D(_000_[2]),
    .Q(dataout0[2])
  );
  DFF _121_ (
    .C(clk),
    .D(_000_[3]),
    .Q(dataout0[3])
  );
  DFF _122_ (
    .C(clk),
    .D(_000_[4]),
    .Q(dataout0[4])
  );
  DFF _123_ (
    .C(clk),
    .D(_000_[5]),
    .Q(dataout0[5])
  );
  DFF _124_ (
    .C(clk),
    .D(_001_[0]),
    .Q(dataout1[0])
  );
  DFF _125_ (
    .C(clk),
    .D(_001_[1]),
    .Q(dataout1[1])
  );
  DFF _126_ (
    .C(clk),
    .D(_001_[2]),
    .Q(dataout1[2])
  );
  DFF _127_ (
    .C(clk),
    .D(_001_[3]),
    .Q(dataout1[3])
  );
  DFF _128_ (
    .C(clk),
    .D(_001_[4]),
    .Q(dataout1[4])
  );
  DFF _129_ (
    .C(clk),
    .D(_001_[5]),
    .Q(dataout1[5])
  );
  DFF _130_ (
    .C(clk),
    .D(_002_),
    .Q(valid_0)
  );
  DFF _131_ (
    .C(clk),
    .D(_003_),
    .Q(valid_1)
  );
endmodule

Memoria/cmos_cells.v

module BUF(A, Y);
input A;
output Y;
assign Y = A;
endmodule

module NOT(A, Y);
input A;
output Y;
assign Y = ~A;
endmodule

module NAND(A, B, Y);
input A, B;
output Y;
assign Y = ~(A & B);
endmodule

module NOR(A, B, Y);
input A, B;
output Y;
assign Y = ~(A | B);
endmodule

module DFF(C, D, Q);
input C, D;
output reg Q;
always @(posedge C)
	Q <= D;
endmodule

module DFFSR(C, D, Q, S, R);
input C, D, S, R;
output reg Q;
always @(posedge C, posedge S, posedge R)
	if (S)
		Q <= 1'b1;
	else if (R)
		Q <= 1'b0;
	else
		Q <= D;
endmodule

Demux/Demux_D0_D1/Demux_D0_D1.vcd
$date
	Wed Jul  3 14:44:45 2019
$end
$version
	Icarus Verilog
$end
$timescale
	100ps
$end
$scope module BUF $end
$var wire 1 ! A $end
$var wire 1 " Y $end
$upscope $end
$scope module DFFSR $end
$var wire 1 # C $end
$var wire 1 $ D $end
$var wire 1 % R $end
$var wire 1 & S $end
$var reg 1 ' Q $end
$upscope $end
$scope module Demux_D0_D1_Estructural $end
$var wire 1 ( clk $end
$var wire 6 ) data_in [5:0] $end
$var wire 1 * reset_L $end
$var wire 1 + valid_in $end
$var wire 1 , valid_1 $end
$var wire 1 - valid_0 $end
$var wire 6 . dataout1 [5:0] $end
$var wire 6 / dataout0 [5:0] $end
$var wire 1 0 _053_ $end
$var wire 1 1 _052_ $end
$var wire 1 2 _051_ $end
$var wire 1 3 _050_ $end
$var wire 1 4 _049_ $end
$var wire 1 5 _048_ $end
$var wire 1 6 _047_ $end
$var wire 1 7 _046_ $end
$var wire 1 8 _045_ $end
$var wire 1 9 _044_ $end
$var wire 1 : _043_ $end
$var wire 1 ; _042_ $end
$var wire 1 < _041_ $end
$var wire 1 = _040_ $end
$var wire 1 > _039_ $end
$var wire 1 ? _038_ $end
$var wire 1 @ _037_ $end
$var wire 1 A _036_ $end
$var wire 1 B _035_ $end
$var wire 1 C _034_ $end
$var wire 1 D _033_ $end
$var wire 1 E _032_ $end
$var wire 1 F _031_ $end
$var wire 1 G _030_ $end
$var wire 1 H _029_ $end
$var wire 1 I _028_ $end
$var wire 1 J _027_ $end
$var wire 1 K _026_ $end
$var wire 1 L _025_ $end
$var wire 1 M _024_ $end
$var wire 1 N _023_ $end
$var wire 1 O _022_ $end
$var wire 1 P _021_ $end
$var wire 1 Q _020_ $end
$var wire 1 R _019_ $end
$var wire 1 S _018_ $end
$var wire 1 T _017_ $end
$var wire 1 U _016_ $end
$var wire 1 V _015_ $end
$var wire 1 W _014_ $end
$var wire 1 X _013_ $end
$var wire 1 Y _012_ $end
$var wire 1 Z _011_ $end
$var wire 1 [ _010_ $end
$var wire 1 \ _009_ $end
$var wire 1 ] _008_ $end
$var wire 1 ^ _007_ $end
$var wire 1 _ _006_ $end
$var wire 1 ` _005_ $end
$var wire 1 a _004_ $end
$var wire 1 b _003_ $end
$var wire 1 c _002_ $end
$var wire 6 d _001_ [5:0] $end
$var wire 6 e _000_ [5:0] $end
$scope module _054_ $end
$var wire 1 f A $end
$var wire 1 a Y $end
$upscope $end
$scope module _055_ $end
$var wire 1 + A $end
$var wire 1 * B $end
$var wire 1 ` Y $end
$upscope $end
$scope module _056_ $end
$var wire 1 ` A $end
$var wire 1 a B $end
$var wire 1 b Y $end
$upscope $end
$scope module _057_ $end
$var wire 1 ` A $end
$var wire 1 g B $end
$var wire 1 c Y $end
$upscope $end
$scope module _058_ $end
$var wire 1 + B $end
$var wire 1 _ Y $end
$var wire 1 , A $end
$upscope $end
$scope module _059_ $end
$var wire 1 _ A $end
$var wire 1 b B $end
$var wire 1 ^ Y $end
$upscope $end
$scope module _060_ $end
$var wire 1 * A $end
$var wire 1 ] Y $end
$upscope $end
$scope module _061_ $end
$var wire 1 h A $end
$var wire 1 \ Y $end
$upscope $end
$scope module _062_ $end
$var wire 1 \ A $end
$var wire 1 ] B $end
$var wire 1 [ Y $end
$upscope $end
$scope module _063_ $end
$var wire 1 [ A $end
$var wire 1 ^ B $end
$var wire 1 Z Y $end
$upscope $end
$scope module _064_ $end
$var wire 1 b A $end
$var wire 1 i B $end
$var wire 1 Y Y $end
$upscope $end
$scope module _065_ $end
$var wire 1 Y A $end
$var wire 1 Z B $end
$var wire 1 j Y $end
$upscope $end
$scope module _066_ $end
$var wire 1 k A $end
$var wire 1 X Y $end
$upscope $end
$scope module _067_ $end
$var wire 1 X A $end
$var wire 1 ] B $end
$var wire 1 W Y $end
$upscope $end
$scope module _068_ $end
$var wire 1 W A $end
$var wire 1 ^ B $end
$var wire 1 V Y $end
$upscope $end
$scope module _069_ $end
$var wire 1 b A $end
$var wire 1 l B $end
$var wire 1 U Y $end
$upscope $end
$scope module _070_ $end
$var wire 1 U A $end
$var wire 1 V B $end
$var wire 1 m Y $end
$upscope $end
$scope module _071_ $end
$var wire 1 n A $end
$var wire 1 T Y $end
$upscope $end
$scope module _072_ $end
$var wire 1 T A $end
$var wire 1 ] B $end
$var wire 1 S Y $end
$upscope $end
$scope module _073_ $end
$var wire 1 S A $end
$var wire 1 ^ B $end
$var wire 1 R Y $end
$upscope $end
$scope module _074_ $end
$var wire 1 b A $end
$var wire 1 o B $end
$var wire 1 Q Y $end
$upscope $end
$scope module _075_ $end
$var wire 1 Q A $end
$var wire 1 R B $end
$var wire 1 p Y $end
$upscope $end
$scope module _076_ $end
$var wire 1 q A $end
$var wire 1 P Y $end
$upscope $end
$scope module _077_ $end
$var wire 1 P A $end
$var wire 1 ] B $end
$var wire 1 O Y $end
$upscope $end
$scope module _078_ $end
$var wire 1 O A $end
$var wire 1 ^ B $end
$var wire 1 N Y $end
$upscope $end
$scope module _079_ $end
$var wire 1 b A $end
$var wire 1 r B $end
$var wire 1 M Y $end
$upscope $end
$scope module _080_ $end
$var wire 1 M A $end
$var wire 1 N B $end
$var wire 1 s Y $end
$upscope $end
$scope module _081_ $end
$var wire 1 + A $end
$var wire 1 L Y $end
$upscope $end
$scope module _082_ $end
$var wire 1 L A $end
$var wire 1 ] B $end
$var wire 1 K Y $end
$upscope $end
$scope module _083_ $end
$var wire 1 K A $end
$var wire 1 t B $end
$var wire 1 J Y $end
$upscope $end
$scope module _084_ $end
$var wire 1 _ A $end
$var wire 1 I Y $end
$upscope $end
$scope module _085_ $end
$var wire 1 u A $end
$var wire 1 H Y $end
$upscope $end
$scope module _086_ $end
$var wire 1 H A $end
$var wire 1 ] B $end
$var wire 1 G Y $end
$upscope $end
$scope module _087_ $end
$var wire 1 G A $end
$var wire 1 I B $end
$var wire 1 F Y $end
$upscope $end
$scope module _088_ $end
$var wire 1 F A $end
$var wire 1 J B $end
$var wire 1 v Y $end
$upscope $end
$scope module _089_ $end
$var wire 1 w A $end
$var wire 1 E Y $end
$upscope $end
$scope module _090_ $end
$var wire 1 E A $end
$var wire 1 ] B $end
$var wire 1 D Y $end
$upscope $end
$scope module _091_ $end
$var wire 1 D A $end
$var wire 1 ^ B $end
$var wire 1 C Y $end
$upscope $end
$scope module _092_ $end
$var wire 1 b A $end
$var wire 1 x B $end
$var wire 1 B Y $end
$upscope $end
$scope module _093_ $end
$var wire 1 B A $end
$var wire 1 C B $end
$var wire 1 y Y $end
$upscope $end
$scope module _094_ $end
$var wire 1 c A $end
$var wire 1 z B $end
$var wire 1 A Y $end
$upscope $end
$scope module _095_ $end
$var wire 1 + A $end
$var wire 1 ] B $end
$var wire 1 @ Y $end
$upscope $end
$scope module _096_ $end
$var wire 1 @ A $end
$var wire 1 ? Y $end
$var wire 1 - B $end
$upscope $end
$scope module _097_ $end
$var wire 1 ? A $end
$var wire 1 J B $end
$var wire 1 > Y $end
$upscope $end
$scope module _098_ $end
$var wire 1 > A $end
$var wire 1 { B $end
$var wire 1 = Y $end
$upscope $end
$scope module _099_ $end
$var wire 1 = A $end
$var wire 1 A B $end
$var wire 1 | Y $end
$upscope $end
$scope module _100_ $end
$var wire 1 c A $end
$var wire 1 } B $end
$var wire 1 < Y $end
$upscope $end
$scope module _101_ $end
$var wire 1 > A $end
$var wire 1 ~ B $end
$var wire 1 ; Y $end
$upscope $end
$scope module _102_ $end
$var wire 1 ; A $end
$var wire 1 < B $end
$var wire 1 !" Y $end
$upscope $end
$scope module _103_ $end
$var wire 1 c A $end
$var wire 1 "" B $end
$var wire 1 : Y $end
$upscope $end
$scope module _104_ $end
$var wire 1 > A $end
$var wire 1 #" B $end
$var wire 1 9 Y $end
$upscope $end
$scope module _105_ $end
$var wire 1 9 A $end
$var wire 1 : B $end
$var wire 1 $" Y $end
$upscope $end
$scope module _106_ $end
$var wire 1 c A $end
$var wire 1 %" B $end
$var wire 1 8 Y $end
$upscope $end
$scope module _107_ $end
$var wire 1 > A $end
$var wire 1 &" B $end
$var wire 1 7 Y $end
$upscope $end
$scope module _108_ $end
$var wire 1 7 A $end
$var wire 1 8 B $end
$var wire 1 '" Y $end
$upscope $end
$scope module _109_ $end
$var wire 1 (" A $end
$var wire 1 6 Y $end
$upscope $end
$scope module _110_ $end
$var wire 1 5 Y $end
$var wire 1 - A $end
$upscope $end
$scope module _111_ $end
$var wire 1 L A $end
$var wire 1 * B $end
$var wire 1 4 Y $end
$upscope $end
$scope module _112_ $end
$var wire 1 4 A $end
$var wire 1 5 B $end
$var wire 1 3 Y $end
$upscope $end
$scope module _113_ $end
$var wire 1 3 A $end
$var wire 1 b B $end
$var wire 1 2 Y $end
$upscope $end
$scope module _114_ $end
$var wire 1 2 A $end
$var wire 1 6 B $end
$var wire 1 )" Y $end
$upscope $end
$scope module _115_ $end
$var wire 1 c A $end
$var wire 1 *" B $end
$var wire 1 1 Y $end
$upscope $end
$scope module _116_ $end
$var wire 1 > A $end
$var wire 1 +" B $end
$var wire 1 0 Y $end
$upscope $end
$scope module _117_ $end
$var wire 1 0 A $end
$var wire 1 1 B $end
$var wire 1 ," Y $end
$upscope $end
$scope module _118_ $end
$var wire 1 ( C $end
$var wire 1 -" D $end
$var reg 1 ." Q $end
$upscope $end
$scope module _119_ $end
$var wire 1 ( C $end
$var wire 1 /" D $end
$var reg 1 0" Q $end
$upscope $end
$scope module _120_ $end
$var wire 1 ( C $end
$var wire 1 1" D $end
$var reg 1 2" Q $end
$upscope $end
$scope module _121_ $end
$var wire 1 ( C $end
$var wire 1 3" D $end
$var reg 1 4" Q $end
$upscope $end
$scope module _122_ $end
$var wire 1 ( C $end
$var wire 1 5" D $end
$var reg 1 6" Q $end
$upscope $end
$scope module _123_ $end
$var wire 1 ( C $end
$var wire 1 7" D $end
$var reg 1 8" Q $end
$upscope $end
$scope module _124_ $end
$var wire 1 ( C $end
$var wire 1 9" D $end
$var reg 1 :" Q $end
$upscope $end
$scope module _125_ $end
$var wire 1 ( C $end
$var wire 1 ;" D $end
$var reg 1 <" Q $end
$upscope $end
$scope module _126_ $end
$var wire 1 ( C $end
$var wire 1 =" D $end
$var reg 1 >" Q $end
$upscope $end
$scope module _127_ $end
$var wire 1 ( C $end
$var wire 1 ?" D $end
$var reg 1 @" Q $end
$upscope $end
$scope module _128_ $end
$var wire 1 ( C $end
$var wire 1 A" D $end
$var reg 1 B" Q $end
$upscope $end
$scope module _129_ $end
$var wire 1 ( C $end
$var wire 1 C" D $end
$var reg 1 D" Q $end
$upscope $end
$scope module _130_ $end
$var wire 1 ( C $end
$var wire 1 c D $end
$var reg 1 - Q $end
$upscope $end
$scope module _131_ $end
$var wire 1 ( C $end
$var wire 1 b D $end
$var reg 1 , Q $end
$upscope $end
$upscope $end
$scope module Test_Bench $end
$var wire 6 E" dataout0 [5:0] $end
$var wire 6 F" dataout1 [5:0] $end
$var wire 1 G" valid_0 $end
$var wire 1 H" valid_1 $end
$var wire 1 I" valid_in $end
$var wire 1 J" reset_L $end
$var wire 6 K" data_in [5:0] $end
$var wire 1 L" clk $end
$scope module DM $end
$var wire 1 I" valid_in $end
$var wire 1 J" reset_L $end
$var wire 6 M" data_in [5:0] $end
$var wire 1 L" clk $end
$var reg 6 N" dataout0 [5:0] $end
$var reg 6 O" dataout1 [5:0] $end
$var reg 1 P" selectorL1 $end
$var reg 1 Q" valid_0 $end
$var reg 1 R" valid_1 $end
$upscope $end
$scope module DMEstr $end
$var wire 1 I" valid_in $end
$var wire 1 J" reset_L $end
$var wire 6 S" data_in [5:0] $end
$var wire 1 L" clk $end
$var reg 6 T" dataout0 [5:0] $end
$var reg 6 U" dataout1 [5:0] $end
$var reg 1 V" selectorL1 $end
$var reg 1 W" valid_0 $end
$var reg 1 X" valid_1 $end
$upscope $end
$scope module PDMux $end
$var wire 6 Y" dataout0 [5:0] $end
$var wire 6 Z" dataout1 [5:0] $end
$var wire 1 G" valid_0 $end
$var wire 1 H" valid_1 $end
$var reg 1 L" clk $end
$var reg 6 [" data_in [5:0] $end
$var reg 1 J" reset_L $end
$var reg 1 I" valid_in $end
$upscope $end
$upscope $end
$enddefinitions $end
#0
$dumpvars
bx ["
bx Z"
bx Y"
xX"
xW"
0V"
bx U"
bx T"
bx S"
xR"
xQ"
0P"
bx O"
bx N"
bx M"
0L"
bx K"
0J"
xI"
xH"
xG"
bx F"
bx E"
xD"
xC"
xB"
xA"
x@"
x?"
x>"
x="
x<"
x;"
x:"
x9"
x8"
x7"
x6"
x5"
x4"
x3"
x2"
x1"
x0"
x/"
x."
x-"
x,"
x+"
z*"
x)"
x("
x'"
x&"
z%"
x$"
x#"
z""
x!"
x~
z}
x|
x{
zz
xy
zx
xw
xv
xu
zt
xs
zr
xq
xp
zo
xn
xm
zl
xk
xj
zi
xh
zg
zf
bx e
bx d
xc
xb
za
x`
x_
x^
z]
x\
x[
xZ
xY
xX
xW
xV
xU
xT
xS
xR
xQ
xP
xO
xN
xM
zL
xK
xJ
xI
xH
xG
xF
xE
xD
xC
xB
xA
x@
x?
x>
x=
x<
x;
x:
x9
x8
x7
x6
x5
x4
x3
x2
x1
x0
bx /
bx .
x-
x,
z+
z*
bz )
z(
x'
z&
z%
z$
z#
z"
z!
$end
#20
1P"
1V"
0H"
0R"
0G"
0Q"
b0 E"
b0 Y"
b0 N"
b0 F"
b0 Z"
b0 O"
0X"
0W"
b0 T"
b0 U"
1J"
0I"
b110100 K"
b110100 M"
b110100 S"
b110100 ["
1L"
#40
0L"
#60
1I"
b110010 K"
b110010 M"
b110010 S"
b110010 ["
1L"
#80
0L"
#100
1R"
b110010 O"
1H"
1X"
b110010 F"
b110010 Z"
b110010 U"
b110111 K"
b110111 M"
b110111 S"
b110111 ["
1L"
#120
0L"
#140
0I"
b111110 K"
b111110 M"
b111110 S"
b111110 ["
b110111 U"
b110111 F"
b110111 Z"
b110111 O"
1L"
#160
0L"
#180
0P"
0V"
0R"
0H"
0X"
b101101 K"
b101101 M"
b101101 S"
b101101 ["
1L"
#200
0L"
#220
1V"
1P"
1I"
b10010 K"
b10010 M"
b10010 S"
b10010 ["
b0 U"
b0 F"
b0 Z"
b0 O"
1L"
#240
0L"
#260
1R"
b10010 O"
1H"
1X"
b10010 F"
b10010 Z"
b10010 U"
b10011 K"
b10011 M"
b10011 S"
b10011 ["
1L"
#280
0L"
#300
0V"
0P"
0J"
b10011 U"
b10011 F"
b10011 Z"
b10011 O"
1L"
#320
0L"
#340
1P"
1V"
0R"
b0 O"
0H"
0X"
b0 F"
b0 Z"
b0 U"
1J"
1L"
#360
0L"
#380
0V"
0P"
b100011 K"
b100011 M"
b100011 S"
b100011 ["
1X"
b10011 U"
1H"
1R"
b10011 F"
b10011 Z"
b10011 O"
1L"
#400
0L"
#420
0R"
1Q"
b100011 N"
0H"
0X"
1G"
1W"
b100011 E"
b100011 Y"
b100011 T"
b100 K"
b100 M"
b100 S"
b100 ["
1L"
#440
0L"
#460
0I"
b100101 K"
b100101 M"
b100101 S"
b100101 ["
b100 T"
b100 E"
b100 Y"
b100 N"
1L"
#480
0L"
#500
b0 O"
0Q"
b0 F"
b0 Z"
b0 U"
0G"
0W"
1L"
#520
0L"
#540
b0 T"
b0 E"
b0 Y"
b0 N"
1L"
